[
  {
    "id": 0,
    "name": "奥迪"
  },
  {
    "id": 1,
    "name": "一汽-大众奥迪"
  },
  {
    "id": 2,
    "name": "奥迪A3两厢"
  },
  {
    "id": 3,
    "name": "奥迪A3三厢"
  },
  {
    "id": 4,
    "name": "奥迪A4L"
  },
  {
    "id": 5,
    "name": "奥迪A6L"
  },
  {
    "id": 6,
    "name": "奥迪Q2L"
  },
  {
    "id": 7,
    "name": "奥迪Q2L e-tron"
  },
  {
    "id": 8,
    "name": "奥迪Q3"
  },
  {
    "id": 9,
    "name": "奥迪Q5L"
  },
  {
    "id": 10,
    "name": "进口奥迪"
  },
  {
    "id": 11,
    "name": "奥迪A3"
  },
  {
    "id": 12,
    "name": "奥迪A4 Allroad"
  },
  {
    "id": 13,
    "name": "奥迪A5"
  },
  {
    "id": 14,
    "name": "奥迪A6 Avant"
  },
  {
    "id": 15,
    "name": "奥迪A6 Allroad"
  },
  {
    "id": 16,
    "name": "奥迪A7"
  },
  {
    "id": 17,
    "name": "奥迪A8L"
  },
  {
    "id": 18,
    "name": "奥迪Q7"
  },
  {
    "id": 19,
    "name": "奥迪Q7 e-tron"
  },
  {
    "id": 20,
    "name": "奥迪Q8"
  },
  {
    "id": 21,
    "name": "奥迪TT"
  },
  {
    "id": 22,
    "name": "奥迪e-tron"
  },
  {
    "id": 23,
    "name": "Audi Sport"
  },
  {
    "id": 24,
    "name": "奥迪S3"
  },
  {
    "id": 25,
    "name": "奥迪S4"
  },
  {
    "id": 26,
    "name": "奥迪S5"
  },
  {
    "id": 27,
    "name": "奥迪S6"
  },
  {
    "id": 28,
    "name": "奥迪S7"
  },
  {
    "id": 29,
    "name": "奥迪TTS"
  },
  {
    "id": 30,
    "name": "奥迪RS3"
  },
  {
    "id": 31,
    "name": "奥迪RS4 Avant"
  },
  {
    "id": 32,
    "name": "奥迪RS5"
  },
  {
    "id": 33,
    "name": "奥迪RS6 Avant"
  },
  {
    "id": 34,
    "name": "奥迪RS7"
  },
  {
    "id": 35,
    "name": "奥迪TT RS"
  },
  {
    "id": 36,
    "name": "奥迪R8"
  },
  {
    "id": 37,
    "name": "阿尔法·罗密欧"
  },
  {
    "id": 38,
    "name": "阿尔法·罗密欧"
  },
  {
    "id": 39,
    "name": "Giulia"
  },
  {
    "id": 40,
    "name": "Stelvio"
  },
  {
    "id": 41,
    "name": "阿斯顿·马丁"
  },
  {
    "id": 42,
    "name": "阿斯顿·马丁"
  },
  {
    "id": 43,
    "name": "Rapide"
  },
  {
    "id": 44,
    "name": "Rapide E"
  },
  {
    "id": 45,
    "name": "V8 Vantage"
  },
  {
    "id": 46,
    "name": "Vanquish"
  },
  {
    "id": 47,
    "name": "DB11"
  },
  {
    "id": 48,
    "name": "DBS"
  },
  {
    "id": 49,
    "name": "ARCFOX"
  },
  {
    "id": 50,
    "name": "北汽集团"
  },
  {
    "id": 51,
    "name": "ARCFOX-7"
  },
  {
    "id": 52,
    "name": "ALPINA"
  },
  {
    "id": 53,
    "name": "ALPINA"
  },
  {
    "id": 54,
    "name": "ALPINA B4"
  },
  {
    "id": 55,
    "name": "爱驰"
  },
  {
    "id": 56,
    "name": "爱驰"
  },
  {
    "id": 57,
    "name": "爱驰U5"
  },
  {
    "id": 58,
    "name": "艾康尼克"
  },
  {
    "id": 59,
    "name": "艾康尼克"
  },
  {
    "id": 60,
    "name": "艾康尼克七系"
  },
  {
    "id": 61,
    "name": "奔驰"
  },
  {
    "id": 62,
    "name": "进口奔驰"
  },
  {
    "id": 63,
    "name": "奔驰B级"
  },
  {
    "id": 64,
    "name": "奔驰CLA级"
  },
  {
    "id": 65,
    "name": "奔驰C级"
  },
  {
    "id": 66,
    "name": "奔驰C级旅行版"
  },
  {
    "id": 67,
    "name": "奔驰E级"
  },
  {
    "id": 68,
    "name": "奔驰CLS级"
  },
  {
    "id": 69,
    "name": "奔驰S级"
  },
  {
    "id": 70,
    "name": "奔驰GLC"
  },
  {
    "id": 71,
    "name": "奔驰GLE"
  },
  {
    "id": 72,
    "name": "奔驰GLS"
  },
  {
    "id": 73,
    "name": "奔驰G级"
  },
  {
    "id": 74,
    "name": "奔驰R级"
  },
  {
    "id": 75,
    "name": "奔驰SLC级"
  },
  {
    "id": 76,
    "name": "奔驰SL级"
  },
  {
    "id": 77,
    "name": "梅赛德斯-AMG"
  },
  {
    "id": 78,
    "name": "奔驰A级AMG"
  },
  {
    "id": 79,
    "name": "奔驰CLA AMG"
  },
  {
    "id": 80,
    "name": "奔驰C AMG"
  },
  {
    "id": 81,
    "name": "奔驰E AMG"
  },
  {
    "id": 82,
    "name": "奔驰S AMG"
  },
  {
    "id": 83,
    "name": "奔驰GLA AMG"
  },
  {
    "id": 84,
    "name": "奔驰GLC AMG"
  },
  {
    "id": 85,
    "name": "奔驰GLE AMG"
  },
  {
    "id": 86,
    "name": "奔驰GLS AMG"
  },
  {
    "id": 87,
    "name": "奔驰G AMG"
  },
  {
    "id": 88,
    "name": "奔驰AMG GT"
  },
  {
    "id": 89,
    "name": "梅赛德斯-迈巴赫"
  },
  {
    "id": 90,
    "name": "迈巴赫S级"
  },
  {
    "id": 91,
    "name": "迈巴赫G级"
  },
  {
    "id": 92,
    "name": "北京奔驰"
  },
  {
    "id": 93,
    "name": "奔驰A级"
  },
  {
    "id": 94,
    "name": "奔驰A级AMG"
  },
  {
    "id": 95,
    "name": "奔驰C级"
  },
  {
    "id": 96,
    "name": "奔驰E级"
  },
  {
    "id": 97,
    "name": "奔驰GLA"
  },
  {
    "id": 98,
    "name": "奔驰GLC"
  },
  {
    "id": 99,
    "name": "奔驰EQC"
  },
  {
    "id": 100,
    "name": "福建奔驰"
  },
  {
    "id": 101,
    "name": "奔驰V级"
  },
  {
    "id": 102,
    "name": "威霆"
  },
  {
    "id": 103,
    "name": "凌特"
  },
  {
    "id": 104,
    "name": "梅赛德斯-EQ"
  },
  {
    "id": 105,
    "name": "奔驰EQC"
  },
  {
    "id": 106,
    "name": "宝马"
  },
  {
    "id": 107,
    "name": "华晨宝马"
  },
  {
    "id": 108,
    "name": "宝马1系"
  },
  {
    "id": 109,
    "name": "宝马2系旅行车"
  },
  {
    "id": 110,
    "name": "宝马3系"
  },
  {
    "id": 111,
    "name": "宝马5系"
  },
  {
    "id": 112,
    "name": "宝马5系Le"
  },
  {
    "id": 113,
    "name": "宝马X1"
  },
  {
    "id": 114,
    "name": "宝马X1插电混动"
  },
  {
    "id": 115,
    "name": "宝马X3"
  },
  {
    "id": 116,
    "name": "进口宝马"
  },
  {
    "id": 117,
    "name": "宝马1系两厢"
  },
  {
    "id": 118,
    "name": "宝马2系"
  },
  {
    "id": 119,
    "name": "宝马2系Gran Tourer"
  },
  {
    "id": 120,
    "name": "宝马3系GT"
  },
  {
    "id": 121,
    "name": "宝马4系"
  },
  {
    "id": 122,
    "name": "宝马5系"
  },
  {
    "id": 123,
    "name": "宝马6系"
  },
  {
    "id": 124,
    "name": "宝马6系GT"
  },
  {
    "id": 125,
    "name": "宝马7系"
  },
  {
    "id": 126,
    "name": "宝马X2"
  },
  {
    "id": 127,
    "name": "宝马X4"
  },
  {
    "id": 128,
    "name": "宝马X5"
  },
  {
    "id": 129,
    "name": "宝马X6"
  },
  {
    "id": 130,
    "name": "宝马X7"
  },
  {
    "id": 131,
    "name": "宝马Z4"
  },
  {
    "id": 132,
    "name": "宝马8系"
  },
  {
    "id": 133,
    "name": "宝马M"
  },
  {
    "id": 134,
    "name": "宝马M2"
  },
  {
    "id": 135,
    "name": "宝马M3"
  },
  {
    "id": 136,
    "name": "宝马M4"
  },
  {
    "id": 137,
    "name": "宝马M5"
  },
  {
    "id": 138,
    "name": "宝马M6"
  },
  {
    "id": 139,
    "name": "宝马X3M"
  },
  {
    "id": 140,
    "name": "宝马X4M"
  },
  {
    "id": 141,
    "name": "宝马X5M"
  },
  {
    "id": 142,
    "name": "宝马X6M"
  },
  {
    "id": 143,
    "name": "宝马i"
  },
  {
    "id": 144,
    "name": "宝马i"
  },
  {
    "id": 145,
    "name": "宝马i3"
  },
  {
    "id": 146,
    "name": "宝马i8"
  },
  {
    "id": 147,
    "name": "宝骏"
  },
  {
    "id": 148,
    "name": "上汽通用五菱"
  },
  {
    "id": 149,
    "name": "宝骏E100"
  },
  {
    "id": 150,
    "name": "宝骏E200"
  },
  {
    "id": 151,
    "name": "宝骏310"
  },
  {
    "id": 152,
    "name": "宝骏310W"
  },
  {
    "id": 153,
    "name": "宝骏510"
  },
  {
    "id": 154,
    "name": "宝骏530"
  },
  {
    "id": 155,
    "name": "宝骏RS-5"
  },
  {
    "id": 156,
    "name": "宝骏360"
  },
  {
    "id": 157,
    "name": "宝骏730"
  },
  {
    "id": 158,
    "name": "宝骏RC-6"
  },
  {
    "id": 159,
    "name": "宝骏CN202M"
  },
  {
    "id": 160,
    "name": "保时捷"
  },
  {
    "id": 161,
    "name": "保时捷"
  },
  {
    "id": 162,
    "name": "Panamera"
  },
  {
    "id": 163,
    "name": "Panamera新能源"
  },
  {
    "id": 164,
    "name": "Macan"
  },
  {
    "id": 165,
    "name": "Cayenne"
  },
  {
    "id": 166,
    "name": "Cayenne新能源"
  },
  {
    "id": 167,
    "name": "保时捷718"
  },
  {
    "id": 168,
    "name": "保时捷911"
  },
  {
    "id": 169,
    "name": "别克"
  },
  {
    "id": 170,
    "name": "上汽通用别克"
  },
  {
    "id": 171,
    "name": "凯越"
  },
  {
    "id": 172,
    "name": "英朗"
  },
  {
    "id": 173,
    "name": "阅朗"
  },
  {
    "id": 174,
    "name": "威朗两厢"
  },
  {
    "id": 175,
    "name": "威朗"
  },
  {
    "id": 176,
    "name": "君威"
  },
  {
    "id": 177,
    "name": "君越"
  },
  {
    "id": 178,
    "name": "VELITE 5"
  },
  {
    "id": 179,
    "name": "VELITE 6"
  },
  {
    "id": 180,
    "name": "别克GL6"
  },
  {
    "id": 181,
    "name": "别克GL8"
  },
  {
    "id": 182,
    "name": "昂科拉"
  },
  {
    "id": 183,
    "name": "昂科拉GX"
  },
  {
    "id": 184,
    "name": "昂科威"
  },
  {
    "id": 185,
    "name": "进口别克"
  },
  {
    "id": 186,
    "name": "昂科雷"
  },
  {
    "id": 187,
    "name": "本田"
  },
  {
    "id": 188,
    "name": "广汽本田"
  },
  {
    "id": 189,
    "name": "飞度"
  },
  {
    "id": 190,
    "name": "锋范"
  },
  {
    "id": 191,
    "name": "凌派"
  },
  {
    "id": 192,
    "name": "雅阁"
  },
  {
    "id": 193,
    "name": "缤智"
  },
  {
    "id": 194,
    "name": "冠道"
  },
  {
    "id": 195,
    "name": "奥德赛"
  },
  {
    "id": 196,
    "name": "东风本田"
  },
  {
    "id": 197,
    "name": "竞瑞"
  },
  {
    "id": 198,
    "name": "哥瑞"
  },
  {
    "id": 199,
    "name": "享域"
  },
  {
    "id": 200,
    "name": "思域"
  },
  {
    "id": 201,
    "name": "杰德"
  },
  {
    "id": 202,
    "name": "思铂睿"
  },
  {
    "id": 203,
    "name": "本田INSPIRE"
  },
  {
    "id": 204,
    "name": "本田XR-V"
  },
  {
    "id": 205,
    "name": "本田CR-V"
  },
  {
    "id": 206,
    "name": "本田UR-V"
  },
  {
    "id": 207,
    "name": "艾力绅"
  },
  {
    "id": 208,
    "name": "标致"
  },
  {
    "id": 209,
    "name": "东风标致"
  },
  {
    "id": 210,
    "name": "标致301"
  },
  {
    "id": 211,
    "name": "标致308"
  },
  {
    "id": 212,
    "name": "标致408"
  },
  {
    "id": 213,
    "name": "标致508"
  },
  {
    "id": 214,
    "name": "标致508L PHEV"
  },
  {
    "id": 215,
    "name": "标致2008"
  },
  {
    "id": 216,
    "name": "标致3008"
  },
  {
    "id": 217,
    "name": "标致4008"
  },
  {
    "id": 218,
    "name": "标致5008"
  },
  {
    "id": 219,
    "name": "奔腾"
  },
  {
    "id": 220,
    "name": "一汽奔腾"
  },
  {
    "id": 221,
    "name": "奔腾B30"
  },
  {
    "id": 222,
    "name": "奔腾B30EV"
  },
  {
    "id": 223,
    "name": "奔腾B50"
  },
  {
    "id": 224,
    "name": "奔腾B70"
  },
  {
    "id": 225,
    "name": "奔腾B90"
  },
  {
    "id": 226,
    "name": "奔腾X40"
  },
  {
    "id": 227,
    "name": "奔腾X40EV"
  },
  {
    "id": 228,
    "name": "奔腾T33"
  },
  {
    "id": 229,
    "name": "奔腾T77"
  },
  {
    "id": 230,
    "name": "奔腾X80"
  },
  {
    "id": 231,
    "name": "宝沃"
  },
  {
    "id": 232,
    "name": "宝沃"
  },
  {
    "id": 233,
    "name": "宝沃BX3"
  },
  {
    "id": 234,
    "name": "宝沃BX5"
  },
  {
    "id": 235,
    "name": "宝沃BX6"
  },
  {
    "id": 236,
    "name": "宝沃BX7"
  },
  {
    "id": 237,
    "name": "宝沃BXi7"
  },
  {
    "id": 238,
    "name": "比亚迪"
  },
  {
    "id": 239,
    "name": "比亚迪"
  },
  {
    "id": 240,
    "name": "比亚迪F3"
  },
  {
    "id": 241,
    "name": "速锐"
  },
  {
    "id": 242,
    "name": "比亚迪e1"
  },
  {
    "id": 243,
    "name": "比亚迪e2"
  },
  {
    "id": 244,
    "name": "比亚迪e5"
  },
  {
    "id": 245,
    "name": "秦"
  },
  {
    "id": 246,
    "name": "秦DM"
  },
  {
    "id": 247,
    "name": "秦EV"
  },
  {
    "id": 248,
    "name": "秦Pro"
  },
  {
    "id": 249,
    "name": "秦Pro DM"
  },
  {
    "id": 250,
    "name": "秦Pro EV"
  },
  {
    "id": 251,
    "name": "比亚迪S2"
  },
  {
    "id": 252,
    "name": "元"
  },
  {
    "id": 253,
    "name": "元EV"
  },
  {
    "id": 254,
    "name": "宋"
  },
  {
    "id": 255,
    "name": "宋DM"
  },
  {
    "id": 256,
    "name": "宋EV"
  },
  {
    "id": 257,
    "name": "宋Pro"
  },
  {
    "id": 258,
    "name": "宋Pro DM"
  },
  {
    "id": 259,
    "name": "宋Pro EV"
  },
  {
    "id": 260,
    "name": "宋MAX"
  },
  {
    "id": 261,
    "name": "宋MAX DM"
  },
  {
    "id": 262,
    "name": "宋MAX EV"
  },
  {
    "id": 263,
    "name": "唐"
  },
  {
    "id": 264,
    "name": "唐DM"
  },
  {
    "id": 265,
    "name": "唐EV"
  },
  {
    "id": 266,
    "name": "比亚迪e6"
  },
  {
    "id": 267,
    "name": "比亚迪e-SEED GT"
  },
  {
    "id": 268,
    "name": "宾利"
  },
  {
    "id": 269,
    "name": "宾利"
  },
  {
    "id": 270,
    "name": "欧陆"
  },
  {
    "id": 271,
    "name": "飞驰"
  },
  {
    "id": 272,
    "name": "慕尚"
  },
  {
    "id": 273,
    "name": "添越"
  },
  {
    "id": 274,
    "name": "添越PHEV"
  },
  {
    "id": 275,
    "name": "北京"
  },
  {
    "id": 276,
    "name": "北京汽车"
  },
  {
    "id": 277,
    "name": "北京BJ20"
  },
  {
    "id": 278,
    "name": "北京BJ40"
  },
  {
    "id": 279,
    "name": "北京BJ80"
  },
  {
    "id": 280,
    "name": "北京BJ90"
  },
  {
    "id": 281,
    "name": "北京汽车"
  },
  {
    "id": 282,
    "name": "北京汽车"
  },
  {
    "id": 283,
    "name": "绅宝D50"
  },
  {
    "id": 284,
    "name": "绅宝D70"
  },
  {
    "id": 285,
    "name": "绅宝X25"
  },
  {
    "id": 286,
    "name": "绅宝X35"
  },
  {
    "id": 287,
    "name": "绅宝X55"
  },
  {
    "id": 288,
    "name": "绅宝X65"
  },
  {
    "id": 289,
    "name": "智道"
  },
  {
    "id": 290,
    "name": "智达X3"
  },
  {
    "id": 291,
    "name": "智行"
  },
  {
    "id": 292,
    "name": "北汽新能源"
  },
  {
    "id": 293,
    "name": "北汽新能源"
  },
  {
    "id": 294,
    "name": "EC系列"
  },
  {
    "id": 295,
    "name": "EC3"
  },
  {
    "id": 296,
    "name": "EC5"
  },
  {
    "id": 297,
    "name": "EU系列"
  },
  {
    "id": 298,
    "name": "EU5"
  },
  {
    "id": 299,
    "name": "EU7"
  },
  {
    "id": 300,
    "name": "EX360"
  },
  {
    "id": 301,
    "name": "EX3"
  },
  {
    "id": 302,
    "name": "EX5"
  },
  {
    "id": 303,
    "name": "北汽制造"
  },
  {
    "id": 304,
    "name": "北京汽车"
  },
  {
    "id": 305,
    "name": "BJ 212"
  },
  {
    "id": 306,
    "name": "战旗"
  },
  {
    "id": 307,
    "name": "北京BW007"
  },
  {
    "id": 308,
    "name": "勇士"
  },
  {
    "id": 309,
    "name": "勇士皮卡"
  },
  {
    "id": 310,
    "name": "锐铃"
  },
  {
    "id": 311,
    "name": "北汽昌河"
  },
  {
    "id": 312,
    "name": "北汽昌河"
  },
  {
    "id": 313,
    "name": "昌河北斗星"
  },
  {
    "id": 314,
    "name": "北斗星X5E"
  },
  {
    "id": 315,
    "name": "北汽昌河A6"
  },
  {
    "id": 316,
    "name": "北汽昌河Q25"
  },
  {
    "id": 317,
    "name": "北汽昌河Q35"
  },
  {
    "id": 318,
    "name": "北汽昌河Q7"
  },
  {
    "id": 319,
    "name": "北汽昌河M50"
  },
  {
    "id": 320,
    "name": "北汽昌河M70"
  },
  {
    "id": 321,
    "name": "北汽幻速"
  },
  {
    "id": 322,
    "name": "北汽幻速"
  },
  {
    "id": 323,
    "name": "幻速S2"
  },
  {
    "id": 324,
    "name": "幻速S3"
  },
  {
    "id": 325,
    "name": "幻速S3L"
  },
  {
    "id": 326,
    "name": "幻速S3X"
  },
  {
    "id": 327,
    "name": "幻速S5"
  },
  {
    "id": 328,
    "name": "幻速S6"
  },
  {
    "id": 329,
    "name": "幻速S7"
  },
  {
    "id": 330,
    "name": "幻速C60"
  },
  {
    "id": 331,
    "name": "幻速H2"
  },
  {
    "id": 332,
    "name": "幻速H2V"
  },
  {
    "id": 333,
    "name": "幻速H3"
  },
  {
    "id": 334,
    "name": "幻速H3F"
  },
  {
    "id": 335,
    "name": "幻速H5"
  },
  {
    "id": 336,
    "name": "幻速H6"
  },
  {
    "id": 337,
    "name": "北汽威旺"
  },
  {
    "id": 338,
    "name": "北京汽车"
  },
  {
    "id": 339,
    "name": "威旺S50"
  },
  {
    "id": 340,
    "name": "威旺M20"
  },
  {
    "id": 341,
    "name": "威旺M30"
  },
  {
    "id": 342,
    "name": "威旺M35"
  },
  {
    "id": 343,
    "name": "威旺M50F"
  },
  {
    "id": 344,
    "name": "威旺M60"
  },
  {
    "id": 345,
    "name": "威旺306"
  },
  {
    "id": 346,
    "name": "威旺407EV"
  },
  {
    "id": 347,
    "name": "北汽道达"
  },
  {
    "id": 348,
    "name": "北汽瑞丽"
  },
  {
    "id": 349,
    "name": "道达V8"
  },
  {
    "id": 350,
    "name": "北京清行"
  },
  {
    "id": 351,
    "name": "北京清行"
  },
  {
    "id": 352,
    "name": "竞克400"
  },
  {
    "id": 353,
    "name": "比速汽车"
  },
  {
    "id": 354,
    "name": "比速汽车"
  },
  {
    "id": 355,
    "name": "比速T3"
  },
  {
    "id": 356,
    "name": "比速T5"
  },
  {
    "id": 357,
    "name": "比速T7"
  },
  {
    "id": 358,
    "name": "比速M3"
  },
  {
    "id": 359,
    "name": "博郡汽车"
  },
  {
    "id": 360,
    "name": "博郡汽车"
  },
  {
    "id": 361,
    "name": "博郡iV6"
  },
  {
    "id": 362,
    "name": "博郡iV7"
  },
  {
    "id": 363,
    "name": "拜腾"
  },
  {
    "id": 364,
    "name": "拜腾汽车"
  },
  {
    "id": 365,
    "name": "K-Byte Concept"
  },
  {
    "id": 366,
    "name": "M-Byte Concept"
  },
  {
    "id": 367,
    "name": "长城"
  },
  {
    "id": 368,
    "name": "长城汽车"
  },
  {
    "id": 369,
    "name": "长城C30EV"
  },
  {
    "id": 370,
    "name": "风骏5"
  },
  {
    "id": 371,
    "name": "风骏6"
  },
  {
    "id": 372,
    "name": "风骏7"
  },
  {
    "id": 373,
    "name": "炮"
  },
  {
    "id": 374,
    "name": "炮EV"
  },
  {
    "id": 375,
    "name": "长安"
  },
  {
    "id": 376,
    "name": "长安汽车"
  },
  {
    "id": 377,
    "name": "奔奔"
  },
  {
    "id": 378,
    "name": "悦翔"
  },
  {
    "id": 379,
    "name": "逸动XT"
  },
  {
    "id": 380,
    "name": "逸动DT"
  },
  {
    "id": 381,
    "name": "逸动"
  },
  {
    "id": 382,
    "name": "睿骋"
  },
  {
    "id": 383,
    "name": "睿骋CC"
  },
  {
    "id": 384,
    "name": "长安CS15"
  },
  {
    "id": 385,
    "name": "长安CS35"
  },
  {
    "id": 386,
    "name": "长安CS35PLUS"
  },
  {
    "id": 387,
    "name": "长安CS55"
  },
  {
    "id": 388,
    "name": "长安CS75"
  },
  {
    "id": 389,
    "name": "长安CS75 PLUS"
  },
  {
    "id": 390,
    "name": "长安CS85 COUPE"
  },
  {
    "id": 391,
    "name": "长安CS95"
  },
  {
    "id": 392,
    "name": "凌轩"
  },
  {
    "id": 393,
    "name": "长安新能源"
  },
  {
    "id": 394,
    "name": "长安新能源"
  },
  {
    "id": 395,
    "name": "奔奔EV"
  },
  {
    "id": 396,
    "name": "逸动ET"
  },
  {
    "id": 397,
    "name": "逸动EV"
  },
  {
    "id": 398,
    "name": "逸动PHEV"
  },
  {
    "id": 399,
    "name": "长安CS15EV"
  },
  {
    "id": 400,
    "name": "长安CS75 PHEV"
  },
  {
    "id": 401,
    "name": "长安欧尚"
  },
  {
    "id": 402,
    "name": "长安欧尚"
  },
  {
    "id": 403,
    "name": "欧尚E01"
  },
  {
    "id": 404,
    "name": "尼欧II"
  },
  {
    "id": 405,
    "name": "长安欧尚X70A"
  },
  {
    "id": 406,
    "name": "长安欧尚CX70"
  },
  {
    "id": 407,
    "name": "长安欧尚X7"
  },
  {
    "id": 408,
    "name": "长安欧尚科赛"
  },
  {
    "id": 409,
    "name": "长安欧尚科尚"
  },
  {
    "id": 410,
    "name": "长安欧尚A600"
  },
  {
    "id": 411,
    "name": "长安欧尚A600 EV"
  },
  {
    "id": 412,
    "name": "长安欧尚A800"
  },
  {
    "id": 413,
    "name": "欧尚长行"
  },
  {
    "id": 414,
    "name": "欧诺S"
  },
  {
    "id": 415,
    "name": "长安之星9"
  },
  {
    "id": 416,
    "name": "长安轻型车"
  },
  {
    "id": 417,
    "name": "长安轻型车"
  },
  {
    "id": 418,
    "name": "睿行ES30"
  },
  {
    "id": 419,
    "name": "睿行S50"
  },
  {
    "id": 420,
    "name": "睿行S50T"
  },
  {
    "id": 421,
    "name": "睿行M60"
  },
  {
    "id": 422,
    "name": "睿行M70"
  },
  {
    "id": 423,
    "name": "睿行M80"
  },
  {
    "id": 424,
    "name": "睿行EM80"
  },
  {
    "id": 425,
    "name": "睿行M90"
  },
  {
    "id": 426,
    "name": "神骐F30"
  },
  {
    "id": 427,
    "name": "凯程F70"
  },
  {
    "id": 428,
    "name": "成功"
  },
  {
    "id": 429,
    "name": "航天成功"
  },
  {
    "id": 430,
    "name": "成功V1"
  },
  {
    "id": 431,
    "name": "成功V2"
  },
  {
    "id": 432,
    "name": "成功X1"
  },
  {
    "id": 433,
    "name": "成功BEV6"
  },
  {
    "id": 434,
    "name": "长江EV"
  },
  {
    "id": 435,
    "name": "长江EV"
  },
  {
    "id": 436,
    "name": "逸酷"
  },
  {
    "id": 437,
    "name": "昶洧"
  },
  {
    "id": 438,
    "name": "昶洧"
  },
  {
    "id": 439,
    "name": "昶洧TP-488c"
  },
  {
    "id": 440,
    "name": "刺猬汽车"
  },
  {
    "id": 441,
    "name": "刺猬汽车"
  },
  {
    "id": 442,
    "name": "思迈尔"
  },
  {
    "id": 443,
    "name": "DS"
  },
  {
    "id": 444,
    "name": "长安DS"
  },
  {
    "id": 445,
    "name": "DS 4S"
  },
  {
    "id": 446,
    "name": "DS 5LS"
  },
  {
    "id": 447,
    "name": "DS 5"
  },
  {
    "id": 448,
    "name": "DS 6"
  },
  {
    "id": 449,
    "name": "DS 7"
  },
  {
    "id": 450,
    "name": "大众"
  },
  {
    "id": 451,
    "name": "一汽-大众"
  },
  {
    "id": 452,
    "name": "捷达"
  },
  {
    "id": 453,
    "name": "宝来"
  },
  {
    "id": 454,
    "name": "宝来新能源"
  },
  {
    "id": 455,
    "name": "高尔夫"
  },
  {
    "id": 456,
    "name": "高尔夫GTI"
  },
  {
    "id": 457,
    "name": "高尔夫新能源"
  },
  {
    "id": 458,
    "name": "高尔夫·嘉旅"
  },
  {
    "id": 459,
    "name": "C-TREK蔚领"
  },
  {
    "id": 460,
    "name": "速腾"
  },
  {
    "id": 461,
    "name": "迈腾"
  },
  {
    "id": 462,
    "name": "大众CC"
  },
  {
    "id": 463,
    "name": "T-ROC探歌"
  },
  {
    "id": 464,
    "name": "探岳"
  },
  {
    "id": 465,
    "name": "上汽大众"
  },
  {
    "id": 466,
    "name": "POLO"
  },
  {
    "id": 467,
    "name": "POLO GTI"
  },
  {
    "id": 468,
    "name": "新桑塔纳"
  },
  {
    "id": 469,
    "name": "桑塔纳·浩纳"
  },
  {
    "id": 470,
    "name": "朗逸两厢"
  },
  {
    "id": 471,
    "name": "朗逸"
  },
  {
    "id": 472,
    "name": "朗逸新能源"
  },
  {
    "id": 473,
    "name": "凌渡"
  },
  {
    "id": 474,
    "name": "帕萨特"
  },
  {
    "id": 475,
    "name": "帕萨特PHEV"
  },
  {
    "id": 476,
    "name": "辉昂"
  },
  {
    "id": 477,
    "name": "大众T-Cross"
  },
  {
    "id": 478,
    "name": "途岳"
  },
  {
    "id": 479,
    "name": "途观"
  },
  {
    "id": 480,
    "name": "途观L"
  },
  {
    "id": 481,
    "name": "途观L PHEV"
  },
  {
    "id": 482,
    "name": "途昂"
  },
  {
    "id": 483,
    "name": "途昂X"
  },
  {
    "id": 484,
    "name": "途安L"
  },
  {
    "id": 485,
    "name": "进口大众"
  },
  {
    "id": 486,
    "name": "甲壳虫"
  },
  {
    "id": 487,
    "name": "大众e-Golf"
  },
  {
    "id": 488,
    "name": "高尔夫旅行版"
  },
  {
    "id": 489,
    "name": "蔚揽"
  },
  {
    "id": 490,
    "name": "蔚揽GTE"
  },
  {
    "id": 491,
    "name": "大众Tiguan"
  },
  {
    "id": 492,
    "name": "途锐"
  },
  {
    "id": 493,
    "name": "夏朗"
  },
  {
    "id": 494,
    "name": "凯路威"
  },
  {
    "id": 495,
    "name": "迈特威"
  },
  {
    "id": 496,
    "name": "大众R"
  },
  {
    "id": 497,
    "name": "高尔夫R"
  },
  {
    "id": 498,
    "name": "道奇"
  },
  {
    "id": 499,
    "name": "进口道奇"
  },
  {
    "id": 500,
    "name": "酷威"
  },
  {
    "id": 501,
    "name": "东南"
  },
  {
    "id": 502,
    "name": "东南汽车"
  },
  {
    "id": 503,
    "name": "V3菱悦"
  },
  {
    "id": 504,
    "name": "V5菱致"
  },
  {
    "id": 505,
    "name": "V6菱仕"
  },
  {
    "id": 506,
    "name": "A5翼舞"
  },
  {
    "id": 507,
    "name": "东南DX3"
  },
  {
    "id": 508,
    "name": "东南DX3 EV"
  },
  {
    "id": 509,
    "name": "东南DX7"
  },
  {
    "id": 510,
    "name": "电咖"
  },
  {
    "id": 511,
    "name": "电咖"
  },
  {
    "id": 512,
    "name": "电咖·EV10"
  },
  {
    "id": 513,
    "name": "东风"
  },
  {
    "id": 514,
    "name": "郑州日产"
  },
  {
    "id": 515,
    "name": "帅客"
  },
  {
    "id": 516,
    "name": "帅客EV"
  },
  {
    "id": 517,
    "name": "俊风"
  },
  {
    "id": 518,
    "name": "锐骐6"
  },
  {
    "id": 519,
    "name": "锐骐皮卡"
  },
  {
    "id": 520,
    "name": "锐骐多功能商用车"
  },
  {
    "id": 521,
    "name": "东风汽车"
  },
  {
    "id": 522,
    "name": "俊风ER30"
  },
  {
    "id": 523,
    "name": "俊风E11K"
  },
  {
    "id": 524,
    "name": "俊风E17"
  },
  {
    "id": 525,
    "name": "御风S16"
  },
  {
    "id": 526,
    "name": "御风"
  },
  {
    "id": 527,
    "name": "御风P16"
  },
  {
    "id": 528,
    "name": "东风启辰"
  },
  {
    "id": 529,
    "name": "东风启辰"
  },
  {
    "id": 530,
    "name": "启辰e30"
  },
  {
    "id": 531,
    "name": "启辰D60"
  },
  {
    "id": 532,
    "name": "启辰D60EV"
  },
  {
    "id": 533,
    "name": "启辰T60"
  },
  {
    "id": 534,
    "name": "启辰T60EV"
  },
  {
    "id": 535,
    "name": "启辰T70"
  },
  {
    "id": 536,
    "name": "启辰T90"
  },
  {
    "id": 537,
    "name": "启辰M50V"
  },
  {
    "id": 538,
    "name": "东风风神"
  },
  {
    "id": 539,
    "name": "东风乘用车"
  },
  {
    "id": 540,
    "name": "风神EX1"
  },
  {
    "id": 541,
    "name": "风神A30"
  },
  {
    "id": 542,
    "name": "风神A60"
  },
  {
    "id": 543,
    "name": "奕炫"
  },
  {
    "id": 544,
    "name": "风神E70"
  },
  {
    "id": 545,
    "name": "风神L60"
  },
  {
    "id": 546,
    "name": "东风A9"
  },
  {
    "id": 547,
    "name": "风神AX3"
  },
  {
    "id": 548,
    "name": "风神AX4"
  },
  {
    "id": 549,
    "name": "风神AX5"
  },
  {
    "id": 550,
    "name": "风神AX7"
  },
  {
    "id": 551,
    "name": "风神AX7 PHEV"
  },
  {
    "id": 552,
    "name": "风神AX7 FCV"
  },
  {
    "id": 553,
    "name": "东风风行"
  },
  {
    "id": 554,
    "name": "风行汽车"
  },
  {
    "id": 555,
    "name": "景逸S50"
  },
  {
    "id": 556,
    "name": "风行S50 EV"
  },
  {
    "id": 557,
    "name": "景逸X3"
  },
  {
    "id": 558,
    "name": "景逸X5"
  },
  {
    "id": 559,
    "name": "景逸X6"
  },
  {
    "id": 560,
    "name": "风行SX6"
  },
  {
    "id": 561,
    "name": "风行T5"
  },
  {
    "id": 562,
    "name": "风行T5L"
  },
  {
    "id": 563,
    "name": "风行S500"
  },
  {
    "id": 564,
    "name": "风行F600"
  },
  {
    "id": 565,
    "name": "菱智V3"
  },
  {
    "id": 566,
    "name": "菱智M3"
  },
  {
    "id": 567,
    "name": "菱智M5"
  },
  {
    "id": 568,
    "name": "菱智M5 EV"
  },
  {
    "id": 569,
    "name": "风行M6"
  },
  {
    "id": 570,
    "name": "风行M7"
  },
  {
    "id": 571,
    "name": "风行CM7"
  },
  {
    "id": 572,
    "name": "东风风度"
  },
  {
    "id": 573,
    "name": "郑州日产"
  },
  {
    "id": 574,
    "name": "风度MX5"
  },
  {
    "id": 575,
    "name": "风度MX6"
  },
  {
    "id": 576,
    "name": "东风风光"
  },
  {
    "id": 577,
    "name": "东风小康"
  },
  {
    "id": 578,
    "name": "风光E3"
  },
  {
    "id": 579,
    "name": "风光ix5"
  },
  {
    "id": 580,
    "name": "风光S560"
  },
  {
    "id": 581,
    "name": "风光580"
  },
  {
    "id": 582,
    "name": "风光580 PHEV"
  },
  {
    "id": 583,
    "name": "风光330"
  },
  {
    "id": 584,
    "name": "风光370"
  },
  {
    "id": 585,
    "name": "东风小康"
  },
  {
    "id": 586,
    "name": "东风小康"
  },
  {
    "id": 587,
    "name": "小康C36"
  },
  {
    "id": 588,
    "name": "小康EC36"
  },
  {
    "id": 589,
    "name": "小康C37"
  },
  {
    "id": 590,
    "name": "小康K05S"
  },
  {
    "id": 591,
    "name": "小康K07S"
  },
  {
    "id": 592,
    "name": "东风富康"
  },
  {
    "id": 593,
    "name": "东风富康"
  },
  {
    "id": 594,
    "name": "富康ES500"
  },
  {
    "id": 595,
    "name": "大乘汽车"
  },
  {
    "id": 596,
    "name": "大乘汽车"
  },
  {
    "id": 597,
    "name": "大乘E20"
  },
  {
    "id": 598,
    "name": "大乘G60"
  },
  {
    "id": 599,
    "name": "大乘G60E"
  },
  {
    "id": 600,
    "name": "大乘G60s"
  },
  {
    "id": 601,
    "name": "大乘G70s"
  },
  {
    "id": 602,
    "name": "丰田"
  },
  {
    "id": 603,
    "name": "广汽丰田"
  },
  {
    "id": 604,
    "name": "YARiS L 致炫"
  },
  {
    "id": 605,
    "name": "YARiS L 致享"
  },
  {
    "id": 606,
    "name": "雷凌"
  },
  {
    "id": 607,
    "name": "雷凌双擎E+"
  },
  {
    "id": 608,
    "name": "凯美瑞"
  },
  {
    "id": 609,
    "name": "丰田C-HR"
  },
  {
    "id": 610,
    "name": "丰田C-HR EV"
  },
  {
    "id": 611,
    "name": "汉兰达"
  },
  {
    "id": 612,
    "name": "一汽丰田"
  },
  {
    "id": 613,
    "name": "威驰"
  },
  {
    "id": 614,
    "name": "威驰FS"
  },
  {
    "id": 615,
    "name": "卡罗拉"
  },
  {
    "id": 616,
    "name": "卡罗拉双擎"
  },
  {
    "id": 617,
    "name": "卡罗拉双擎E+"
  },
  {
    "id": 618,
    "name": "皇冠"
  },
  {
    "id": 619,
    "name": "亚洲龙"
  },
  {
    "id": 620,
    "name": "奕泽 IZOA"
  },
  {
    "id": 621,
    "name": "奕泽 IZOA EV"
  },
  {
    "id": 622,
    "name": "RAV4荣放"
  },
  {
    "id": 623,
    "name": "普拉多"
  },
  {
    "id": 624,
    "name": "进口丰田"
  },
  {
    "id": 625,
    "name": "丰田86"
  },
  {
    "id": 626,
    "name": "普瑞维亚"
  },
  {
    "id": 627,
    "name": "威尔法"
  },
  {
    "id": 628,
    "name": "埃尔法"
  },
  {
    "id": 629,
    "name": "福特"
  },
  {
    "id": 630,
    "name": "长安福特"
  },
  {
    "id": 631,
    "name": "福睿斯"
  },
  {
    "id": 632,
    "name": "福克斯两厢"
  },
  {
    "id": 633,
    "name": "福克斯三厢"
  },
  {
    "id": 634,
    "name": "蒙迪欧"
  },
  {
    "id": 635,
    "name": "蒙迪欧插电混动版"
  },
  {
    "id": 636,
    "name": "金牛座"
  },
  {
    "id": 637,
    "name": "翼搏"
  },
  {
    "id": 638,
    "name": "翼虎"
  },
  {
    "id": 639,
    "name": "ESCAPE"
  },
  {
    "id": 640,
    "name": "锐界"
  },
  {
    "id": 641,
    "name": "江铃福特"
  },
  {
    "id": 642,
    "name": "领界"
  },
  {
    "id": 643,
    "name": "领界EV"
  },
  {
    "id": 644,
    "name": "撼路者"
  },
  {
    "id": 645,
    "name": "途睿欧"
  },
  {
    "id": 646,
    "name": "新全顺"
  },
  {
    "id": 647,
    "name": "新世代全顺"
  },
  {
    "id": 648,
    "name": "进口福特"
  },
  {
    "id": 649,
    "name": "福克斯ST"
  },
  {
    "id": 650,
    "name": "福克斯RS"
  },
  {
    "id": 651,
    "name": "Mustang"
  },
  {
    "id": 652,
    "name": "福特GT"
  },
  {
    "id": 653,
    "name": "探险者"
  },
  {
    "id": 654,
    "name": "福特Ranger"
  },
  {
    "id": 655,
    "name": "福特F-150"
  },
  {
    "id": 656,
    "name": "菲亚特"
  },
  {
    "id": 657,
    "name": "广汽菲亚特"
  },
  {
    "id": 658,
    "name": "菲翔"
  },
  {
    "id": 659,
    "name": "致悦"
  },
  {
    "id": 660,
    "name": "法拉利"
  },
  {
    "id": 661,
    "name": "法拉利"
  },
  {
    "id": 662,
    "name": "Portofino"
  },
  {
    "id": 663,
    "name": "California T"
  },
  {
    "id": 664,
    "name": "法拉利488"
  },
  {
    "id": 665,
    "name": "GTC4Lusso"
  },
  {
    "id": 666,
    "name": "812 Superfast"
  },
  {
    "id": 667,
    "name": "SF90 Stradale"
  },
  {
    "id": 668,
    "name": "F8 Tributo"
  },
  {
    "id": 669,
    "name": "F12 berlinetta"
  },
  {
    "id": 670,
    "name": "福田"
  },
  {
    "id": 671,
    "name": "福田汽车"
  },
  {
    "id": 672,
    "name": "风景V3"
  },
  {
    "id": 673,
    "name": "风景V5"
  },
  {
    "id": 674,
    "name": "风景V5纯电动"
  },
  {
    "id": 675,
    "name": "风景"
  },
  {
    "id": 676,
    "name": "风景G7"
  },
  {
    "id": 677,
    "name": "风景G9"
  },
  {
    "id": 678,
    "name": "蒙派克"
  },
  {
    "id": 679,
    "name": "图雅诺"
  },
  {
    "id": 680,
    "name": "萨普"
  },
  {
    "id": 681,
    "name": "福田乘用车"
  },
  {
    "id": 682,
    "name": "福田汽车"
  },
  {
    "id": 683,
    "name": "迦途GT"
  },
  {
    "id": 684,
    "name": "萨瓦纳"
  },
  {
    "id": 685,
    "name": "伽途ix5"
  },
  {
    "id": 686,
    "name": "伽途ix7"
  },
  {
    "id": 687,
    "name": "伽途im6"
  },
  {
    "id": 688,
    "name": "伽途im8"
  },
  {
    "id": 689,
    "name": "拓陆者"
  },
  {
    "id": 690,
    "name": "福迪"
  },
  {
    "id": 691,
    "name": "福迪汽车"
  },
  {
    "id": 692,
    "name": "揽福"
  },
  {
    "id": 693,
    "name": "雄狮F16"
  },
  {
    "id": 694,
    "name": "雄狮F22"
  },
  {
    "id": 695,
    "name": "福汽启腾"
  },
  {
    "id": 696,
    "name": "新龙马"
  },
  {
    "id": 697,
    "name": "启腾V60"
  },
  {
    "id": 698,
    "name": "启腾EX80"
  },
  {
    "id": 699,
    "name": "启腾M70"
  },
  {
    "id": 700,
    "name": "启腾M70EV"
  },
  {
    "id": 701,
    "name": "法拉第未来"
  },
  {
    "id": 702,
    "name": "法拉第未来"
  },
  {
    "id": 703,
    "name": "FF91"
  },
  {
    "id": 704,
    "name": "观致"
  },
  {
    "id": 705,
    "name": "观致汽车"
  },
  {
    "id": 706,
    "name": "观致3轿车"
  },
  {
    "id": 707,
    "name": "观致3 EV"
  },
  {
    "id": 708,
    "name": "观致3五门版"
  },
  {
    "id": 709,
    "name": "观致3都市SUV"
  },
  {
    "id": 710,
    "name": "观致5 SUV"
  },
  {
    "id": 711,
    "name": "Model Young"
  },
  {
    "id": 712,
    "name": "广汽传祺"
  },
  {
    "id": 713,
    "name": "广汽乘用车"
  },
  {
    "id": 714,
    "name": "传祺GA4"
  },
  {
    "id": 715,
    "name": "传祺GA6"
  },
  {
    "id": 716,
    "name": "传祺GA8"
  },
  {
    "id": 717,
    "name": "传祺GS3"
  },
  {
    "id": 718,
    "name": "传祺GS4"
  },
  {
    "id": 719,
    "name": "传祺GS5"
  },
  {
    "id": 720,
    "name": "传祺GS7"
  },
  {
    "id": 721,
    "name": "传祺GS8"
  },
  {
    "id": 722,
    "name": "传祺GM6"
  },
  {
    "id": 723,
    "name": "传祺GM8"
  },
  {
    "id": 724,
    "name": "广汽新能源"
  },
  {
    "id": 725,
    "name": "广汽新能源"
  },
  {
    "id": 726,
    "name": "传祺Aion S"
  },
  {
    "id": 727,
    "name": "传祺GE3"
  },
  {
    "id": 728,
    "name": "传祺GA3S PHEV"
  },
  {
    "id": 729,
    "name": "传祺GS4 PHEV"
  },
  {
    "id": 730,
    "name": "广汽集团"
  },
  {
    "id": 731,
    "name": "广汽丰田"
  },
  {
    "id": 732,
    "name": "广汽丰田ix4"
  },
  {
    "id": 733,
    "name": "广汽本田"
  },
  {
    "id": 734,
    "name": "世锐PHEV"
  },
  {
    "id": 735,
    "name": "国金汽车"
  },
  {
    "id": 736,
    "name": "国金汽车"
  },
  {
    "id": 737,
    "name": "国金GM3"
  },
  {
    "id": 738,
    "name": "国机智骏"
  },
  {
    "id": 739,
    "name": "国机智骏"
  },
  {
    "id": 740,
    "name": "GC1"
  },
  {
    "id": 741,
    "name": "GC2"
  },
  {
    "id": 742,
    "name": "GX5"
  },
  {
    "id": 743,
    "name": "GMC"
  },
  {
    "id": 744,
    "name": "GMC"
  },
  {
    "id": 745,
    "name": "YUKON"
  },
  {
    "id": 746,
    "name": "SAVANA"
  },
  {
    "id": 747,
    "name": "SIERRA"
  },
  {
    "id": 748,
    "name": "哈弗"
  },
  {
    "id": 749,
    "name": "长城汽车"
  },
  {
    "id": 750,
    "name": "哈弗H1"
  },
  {
    "id": 751,
    "name": "哈弗H2"
  },
  {
    "id": 752,
    "name": "哈弗H2S"
  },
  {
    "id": 753,
    "name": "哈弗H4"
  },
  {
    "id": 754,
    "name": "哈弗H5"
  },
  {
    "id": 755,
    "name": "哈弗M6"
  },
  {
    "id": 756,
    "name": "哈弗H6"
  },
  {
    "id": 757,
    "name": "哈弗H6 Coupe"
  },
  {
    "id": 758,
    "name": "哈弗H7"
  },
  {
    "id": 759,
    "name": "哈弗H8"
  },
  {
    "id": 760,
    "name": "哈弗H9"
  },
  {
    "id": 761,
    "name": "哈弗F5"
  },
  {
    "id": 762,
    "name": "哈弗F7"
  },
  {
    "id": 763,
    "name": "哈弗F7x"
  },
  {
    "id": 764,
    "name": "海马"
  },
  {
    "id": 765,
    "name": "海马汽车"
  },
  {
    "id": 766,
    "name": "海马M3"
  },
  {
    "id": 767,
    "name": "海马M6"
  },
  {
    "id": 768,
    "name": "海马S5"
  },
  {
    "id": 769,
    "name": "海马S5青春版"
  },
  {
    "id": 770,
    "name": "海马8S"
  },
  {
    "id": 771,
    "name": "海马新能源"
  },
  {
    "id": 772,
    "name": "爱尚EV"
  },
  {
    "id": 773,
    "name": "海马E3"
  },
  {
    "id": 774,
    "name": "一汽海马"
  },
  {
    "id": 775,
    "name": "福美来轿车"
  },
  {
    "id": 776,
    "name": "福美来F5"
  },
  {
    "id": 777,
    "name": "海马M8"
  },
  {
    "id": 778,
    "name": "福美来F7"
  },
  {
    "id": 779,
    "name": "海马S7"
  },
  {
    "id": 780,
    "name": "红旗"
  },
  {
    "id": 781,
    "name": "一汽红旗"
  },
  {
    "id": 782,
    "name": "红旗H5"
  },
  {
    "id": 783,
    "name": "红旗H7"
  },
  {
    "id": 784,
    "name": "红旗H7 PHEV"
  },
  {
    "id": 785,
    "name": "红旗L5"
  },
  {
    "id": 786,
    "name": "红旗E-HS3"
  },
  {
    "id": 787,
    "name": "红旗HS5"
  },
  {
    "id": 788,
    "name": "红旗HS7"
  },
  {
    "id": 789,
    "name": "华泰"
  },
  {
    "id": 790,
    "name": "华泰汽车"
  },
  {
    "id": 791,
    "name": "路盛S5"
  },
  {
    "id": 792,
    "name": "圣达菲5"
  },
  {
    "id": 793,
    "name": "圣达菲7"
  },
  {
    "id": 794,
    "name": "华泰新能源"
  },
  {
    "id": 795,
    "name": "华泰汽车"
  },
  {
    "id": 796,
    "name": "路盛S1 iEV360"
  },
  {
    "id": 797,
    "name": "路盛S1 EV160B"
  },
  {
    "id": 798,
    "name": "路盛S1 EV160R"
  },
  {
    "id": 799,
    "name": "路盛S5 EV"
  },
  {
    "id": 800,
    "name": "圣达菲2 EV"
  },
  {
    "id": 801,
    "name": "圣达菲5 EV"
  },
  {
    "id": 802,
    "name": "圣达菲7 EV"
  },
  {
    "id": 803,
    "name": "华颂"
  },
  {
    "id": 804,
    "name": "华颂"
  },
  {
    "id": 805,
    "name": "华颂7"
  },
  {
    "id": 806,
    "name": "汉腾汽车"
  },
  {
    "id": 807,
    "name": "汉腾汽车"
  },
  {
    "id": 808,
    "name": "幸福e+"
  },
  {
    "id": 809,
    "name": "汉腾X5"
  },
  {
    "id": 810,
    "name": "汉腾X5 EV"
  },
  {
    "id": 811,
    "name": "汉腾X7"
  },
  {
    "id": 812,
    "name": "汉腾X7 PHEV"
  },
  {
    "id": 813,
    "name": "汉腾X8"
  },
  {
    "id": 814,
    "name": "汉腾V7"
  },
  {
    "id": 815,
    "name": "红星汽车"
  },
  {
    "id": 816,
    "name": "红星汽车"
  },
  {
    "id": 817,
    "name": "闪闪X2"
  },
  {
    "id": 818,
    "name": "黄海"
  },
  {
    "id": 819,
    "name": "黄海汽车"
  },
  {
    "id": 820,
    "name": "黄海N1"
  },
  {
    "id": 821,
    "name": "黄海N1S"
  },
  {
    "id": 822,
    "name": "黄海N2"
  },
  {
    "id": 823,
    "name": "黄海N3"
  },
  {
    "id": 824,
    "name": "黄海N7北美版"
  },
  {
    "id": 825,
    "name": "大柴神至尊版"
  },
  {
    "id": 826,
    "name": "恒天"
  },
  {
    "id": 827,
    "name": "恒天"
  },
  {
    "id": 828,
    "name": "途腾T1"
  },
  {
    "id": 829,
    "name": "途腾T2"
  },
  {
    "id": 830,
    "name": "途腾T3"
  },
  {
    "id": 831,
    "name": "海格"
  },
  {
    "id": 832,
    "name": "苏州金龙"
  },
  {
    "id": 833,
    "name": "海格H5V"
  },
  {
    "id": 834,
    "name": "海格H5C"
  },
  {
    "id": 835,
    "name": "华骐"
  },
  {
    "id": 836,
    "name": "东风悦达起亚"
  },
  {
    "id": 837,
    "name": "华骐300E"
  },
  {
    "id": 838,
    "name": "合创"
  },
  {
    "id": 839,
    "name": "广汽蔚来"
  },
  {
    "id": 840,
    "name": "合创概念车"
  },
  {
    "id": 841,
    "name": "合众新能源"
  },
  {
    "id": 842,
    "name": "合众新能源"
  },
  {
    "id": 843,
    "name": "合众E-TAKE"
  },
  {
    "id": 844,
    "name": "合众U"
  },
  {
    "id": 845,
    "name": "Jeep"
  },
  {
    "id": 846,
    "name": "广汽菲克"
  },
  {
    "id": 847,
    "name": "自由侠"
  },
  {
    "id": 848,
    "name": "指南者"
  },
  {
    "id": 849,
    "name": "自由光"
  },
  {
    "id": 850,
    "name": "指挥官"
  },
  {
    "id": 851,
    "name": "大指挥官"
  },
  {
    "id": 852,
    "name": "大指挥官PHEV"
  },
  {
    "id": 853,
    "name": "进口Jeep"
  },
  {
    "id": 854,
    "name": "牧马人"
  },
  {
    "id": 855,
    "name": "大切诺基"
  },
  {
    "id": 856,
    "name": "吉利"
  },
  {
    "id": 857,
    "name": "吉利汽车"
  },
  {
    "id": 858,
    "name": "金刚"
  },
  {
    "id": 859,
    "name": "远景"
  },
  {
    "id": 860,
    "name": "帝豪"
  },
  {
    "id": 861,
    "name": "帝豪EV"
  },
  {
    "id": 862,
    "name": "帝豪PHEV"
  },
  {
    "id": 863,
    "name": "帝豪GL"
  },
  {
    "id": 864,
    "name": "帝豪GL PHEV"
  },
  {
    "id": 865,
    "name": "缤瑞"
  },
  {
    "id": 866,
    "name": "博瑞"
  },
  {
    "id": 867,
    "name": "博瑞GE"
  },
  {
    "id": 868,
    "name": "博瑞GE PHEV"
  },
  {
    "id": 869,
    "name": "远景X1"
  },
  {
    "id": 870,
    "name": "远景X3"
  },
  {
    "id": 871,
    "name": "远景S1"
  },
  {
    "id": 872,
    "name": "远景SUV"
  },
  {
    "id": 873,
    "name": "帝豪GS"
  },
  {
    "id": 874,
    "name": "帝豪GSe"
  },
  {
    "id": 875,
    "name": "缤越"
  },
  {
    "id": 876,
    "name": "缤越PHEV"
  },
  {
    "id": 877,
    "name": "博越"
  },
  {
    "id": 878,
    "name": "星越"
  },
  {
    "id": 879,
    "name": "星越PHEV"
  },
  {
    "id": 880,
    "name": "嘉际"
  },
  {
    "id": 881,
    "name": "嘉际PHEV"
  },
  {
    "id": 882,
    "name": "几何"
  },
  {
    "id": 883,
    "name": "几何汽车"
  },
  {
    "id": 884,
    "name": "几何A"
  },
  {
    "id": 885,
    "name": "捷豹"
  },
  {
    "id": 886,
    "name": "奇瑞捷豹"
  },
  {
    "id": 887,
    "name": "捷豹XEL"
  },
  {
    "id": 888,
    "name": "捷豹XFL"
  },
  {
    "id": 889,
    "name": "捷豹E-PACE"
  },
  {
    "id": 890,
    "name": "进口捷豹"
  },
  {
    "id": 891,
    "name": "捷豹XE"
  },
  {
    "id": 892,
    "name": "捷豹XF Sportbrake"
  },
  {
    "id": 893,
    "name": "捷豹XJ"
  },
  {
    "id": 894,
    "name": "捷豹F-PACE"
  },
  {
    "id": 895,
    "name": "捷豹I-PACE"
  },
  {
    "id": 896,
    "name": "捷豹F-TYPE"
  },
  {
    "id": 897,
    "name": "捷达"
  },
  {
    "id": 898,
    "name": "一汽-大众"
  },
  {
    "id": 899,
    "name": "捷达VA3"
  },
  {
    "id": 900,
    "name": "捷达VS5"
  },
  {
    "id": 901,
    "name": "捷达VS7"
  },
  {
    "id": 902,
    "name": "捷途"
  },
  {
    "id": 903,
    "name": "奇瑞汽车"
  },
  {
    "id": 904,
    "name": "捷途X70"
  },
  {
    "id": 905,
    "name": "捷途X70S"
  },
  {
    "id": 906,
    "name": "捷途X70S EV"
  },
  {
    "id": 907,
    "name": "捷途X90"
  },
  {
    "id": 908,
    "name": "捷途X95"
  },
  {
    "id": 909,
    "name": "江淮"
  },
  {
    "id": 910,
    "name": "江淮汽车"
  },
  {
    "id": 911,
    "name": "江淮iEV6E"
  },
  {
    "id": 912,
    "name": "江淮iEV7L"
  },
  {
    "id": 913,
    "name": "江淮iEVA50"
  },
  {
    "id": 914,
    "name": "江淮iEVA60"
  },
  {
    "id": 915,
    "name": "江淮IEV7S"
  },
  {
    "id": 916,
    "name": "江淮iEVS4"
  },
  {
    "id": 917,
    "name": "瑞风A60"
  },
  {
    "id": 918,
    "name": "瑞风S2"
  },
  {
    "id": 919,
    "name": "瑞风S3"
  },
  {
    "id": 920,
    "name": "瑞风S4"
  },
  {
    "id": 921,
    "name": "瑞风S5"
  },
  {
    "id": 922,
    "name": "瑞风S7"
  },
  {
    "id": 923,
    "name": "瑞风R3"
  },
  {
    "id": 924,
    "name": "瑞风M3"
  },
  {
    "id": 925,
    "name": "瑞风M4"
  },
  {
    "id": 926,
    "name": "瑞风M5"
  },
  {
    "id": 927,
    "name": "瑞风M6"
  },
  {
    "id": 928,
    "name": "星锐"
  },
  {
    "id": 929,
    "name": "江淮V7"
  },
  {
    "id": 930,
    "name": "帅铃T6"
  },
  {
    "id": 931,
    "name": "帅铃T8"
  },
  {
    "id": 932,
    "name": "奇点"
  },
  {
    "id": 933,
    "name": "奇点汽车"
  },
  {
    "id": 934,
    "name": "奇点iC3"
  },
  {
    "id": 935,
    "name": "奇点iS6"
  },
  {
    "id": 936,
    "name": "金杯"
  },
  {
    "id": 937,
    "name": "华晨华瑞"
  },
  {
    "id": 938,
    "name": "智尚S35"
  },
  {
    "id": 939,
    "name": "金杯S70"
  },
  {
    "id": 940,
    "name": "金典"
  },
  {
    "id": 941,
    "name": "大力神K5"
  },
  {
    "id": 942,
    "name": "华晨鑫源"
  },
  {
    "id": 943,
    "name": "金杯750"
  },
  {
    "id": 944,
    "name": "小海狮"
  },
  {
    "id": 945,
    "name": "新海狮"
  },
  {
    "id": 946,
    "name": "新海狮S"
  },
  {
    "id": 947,
    "name": "华晨雷诺"
  },
  {
    "id": 948,
    "name": "观境"
  },
  {
    "id": 949,
    "name": "领坤EV"
  },
  {
    "id": 950,
    "name": "金杯F50"
  },
  {
    "id": 951,
    "name": "第五代海狮"
  },
  {
    "id": 952,
    "name": "新海狮"
  },
  {
    "id": 953,
    "name": "大海狮"
  },
  {
    "id": 954,
    "name": "阁瑞斯"
  },
  {
    "id": 955,
    "name": "君马"
  },
  {
    "id": 956,
    "name": "君马汽车"
  },
  {
    "id": 957,
    "name": "君马S70"
  },
  {
    "id": 958,
    "name": "君马MEET 3"
  },
  {
    "id": 959,
    "name": "君马SEEK 5"
  },
  {
    "id": 960,
    "name": "江铃"
  },
  {
    "id": 961,
    "name": "江铃汽车"
  },
  {
    "id": 962,
    "name": "宝典"
  },
  {
    "id": 963,
    "name": "域虎3"
  },
  {
    "id": 964,
    "name": "域虎5"
  },
  {
    "id": 965,
    "name": "域虎7"
  },
  {
    "id": 966,
    "name": "域虎9"
  },
  {
    "id": 967,
    "name": "域虎EV"
  },
  {
    "id": 968,
    "name": "特顺"
  },
  {
    "id": 969,
    "name": "江铃集团轻汽"
  },
  {
    "id": 970,
    "name": "江铃集团轻汽"
  },
  {
    "id": 971,
    "name": "骐铃T100"
  },
  {
    "id": 972,
    "name": "骐铃T5"
  },
  {
    "id": 973,
    "name": "骐铃T7"
  },
  {
    "id": 974,
    "name": "骐铃T15"
  },
  {
    "id": 975,
    "name": "江铃集团新能源"
  },
  {
    "id": 976,
    "name": "江铃集团新能源"
  },
  {
    "id": 977,
    "name": "江铃E100B"
  },
  {
    "id": 978,
    "name": "江铃E160L"
  },
  {
    "id": 979,
    "name": "江铃E200L"
  },
  {
    "id": 980,
    "name": "江铃E200N"
  },
  {
    "id": 981,
    "name": "易至EV3"
  },
  {
    "id": 982,
    "name": "江铃E400"
  },
  {
    "id": 983,
    "name": "九龙"
  },
  {
    "id": 984,
    "name": "九龙汽车"
  },
  {
    "id": 985,
    "name": "艾菲"
  },
  {
    "id": 986,
    "name": "九龙A4"
  },
  {
    "id": 987,
    "name": "九龙A5"
  },
  {
    "id": 988,
    "name": "九龙A5S"
  },
  {
    "id": 989,
    "name": "九龙A6"
  },
  {
    "id": 990,
    "name": "金龙"
  },
  {
    "id": 991,
    "name": "金龙客车"
  },
  {
    "id": 992,
    "name": "金威"
  },
  {
    "id": 993,
    "name": "凯锐浩克"
  },
  {
    "id": 994,
    "name": "凯歌"
  },
  {
    "id": 995,
    "name": "凯特"
  },
  {
    "id": 996,
    "name": "Karma"
  },
  {
    "id": 997,
    "name": "Karma"
  },
  {
    "id": 998,
    "name": "Revero"
  },
  {
    "id": 999,
    "name": "Revero GT"
  },
  {
    "id": 1000,
    "name": "凯迪拉克"
  },
  {
    "id": 1001,
    "name": "上汽通用凯迪拉克"
  },
  {
    "id": 1002,
    "name": "凯迪拉克ATS-L"
  },
  {
    "id": 1003,
    "name": "凯迪拉克XTS"
  },
  {
    "id": 1004,
    "name": "凯迪拉克CT6"
  },
  {
    "id": 1005,
    "name": "凯迪拉克XT4"
  },
  {
    "id": 1006,
    "name": "凯迪拉克XT5"
  },
  {
    "id": 1007,
    "name": "凯迪拉克XT6"
  },
  {
    "id": 1008,
    "name": "进口凯迪拉克"
  },
  {
    "id": 1009,
    "name": "凯雷德"
  },
  {
    "id": 1010,
    "name": "克莱斯勒"
  },
  {
    "id": 1011,
    "name": "进口克莱斯勒"
  },
  {
    "id": 1012,
    "name": "300C"
  },
  {
    "id": 1013,
    "name": "大捷龙"
  },
  {
    "id": 1014,
    "name": "大捷龙PHEV"
  },
  {
    "id": 1015,
    "name": "凯翼"
  },
  {
    "id": 1016,
    "name": "凯翼"
  },
  {
    "id": 1017,
    "name": "凯翼C3"
  },
  {
    "id": 1018,
    "name": "凯翼C3R"
  },
  {
    "id": 1019,
    "name": "凯翼E3"
  },
  {
    "id": 1020,
    "name": "凯翼X3"
  },
  {
    "id": 1021,
    "name": "凯翼V3"
  },
  {
    "id": 1022,
    "name": "凯翼X5"
  },
  {
    "id": 1023,
    "name": "开瑞"
  },
  {
    "id": 1024,
    "name": "开瑞汽车"
  },
  {
    "id": 1025,
    "name": "开瑞K50"
  },
  {
    "id": 1026,
    "name": "开瑞K50S"
  },
  {
    "id": 1027,
    "name": "开瑞K50EV"
  },
  {
    "id": 1028,
    "name": "开瑞K60"
  },
  {
    "id": 1029,
    "name": "开瑞K60EV"
  },
  {
    "id": 1030,
    "name": "优优EV"
  },
  {
    "id": 1031,
    "name": "卡威"
  },
  {
    "id": 1032,
    "name": "卡威汽车"
  },
  {
    "id": 1033,
    "name": "悍马纯电动"
  },
  {
    "id": 1034,
    "name": "路易斯"
  },
  {
    "id": 1035,
    "name": "卡威K1"
  },
  {
    "id": 1036,
    "name": "卡威K150GT"
  },
  {
    "id": 1037,
    "name": "LITE"
  },
  {
    "id": 1038,
    "name": "北汽新能源"
  },
  {
    "id": 1039,
    "name": "LITE"
  },
  {
    "id": 1040,
    "name": "铃木"
  },
  {
    "id": 1041,
    "name": "长安铃木"
  },
  {
    "id": 1042,
    "name": "奥拓"
  },
  {
    "id": 1043,
    "name": "雨燕"
  },
  {
    "id": 1044,
    "name": "天语 SX4"
  },
  {
    "id": 1045,
    "name": "启悦"
  },
  {
    "id": 1046,
    "name": "骁途"
  },
  {
    "id": 1047,
    "name": "维特拉"
  },
  {
    "id": 1048,
    "name": "昌河铃木"
  },
  {
    "id": 1049,
    "name": "北斗星"
  },
  {
    "id": 1050,
    "name": "北斗星X5"
  },
  {
    "id": 1051,
    "name": "进口铃木"
  },
  {
    "id": 1052,
    "name": "英格尼斯"
  },
  {
    "id": 1053,
    "name": "吉姆尼"
  },
  {
    "id": 1054,
    "name": "超级维特拉"
  },
  {
    "id": 1055,
    "name": "路虎"
  },
  {
    "id": 1056,
    "name": "奇瑞路虎"
  },
  {
    "id": 1057,
    "name": "发现神行"
  },
  {
    "id": 1058,
    "name": "揽胜极光"
  },
  {
    "id": 1059,
    "name": "进口路虎"
  },
  {
    "id": 1060,
    "name": "揽胜极光"
  },
  {
    "id": 1061,
    "name": "揽胜星脉"
  },
  {
    "id": 1062,
    "name": "发现"
  },
  {
    "id": 1063,
    "name": "揽胜运动版"
  },
  {
    "id": 1064,
    "name": "揽胜运动版P400e"
  },
  {
    "id": 1065,
    "name": "揽胜"
  },
  {
    "id": 1066,
    "name": "揽胜P400e"
  },
  {
    "id": 1067,
    "name": "雷诺"
  },
  {
    "id": 1068,
    "name": "东风雷诺"
  },
  {
    "id": 1069,
    "name": "科雷嘉"
  },
  {
    "id": 1070,
    "name": "科雷傲"
  },
  {
    "id": 1071,
    "name": "雷诺e诺"
  },
  {
    "id": 1072,
    "name": "进口雷诺"
  },
  {
    "id": 1073,
    "name": "风朗"
  },
  {
    "id": 1074,
    "name": "卡缤"
  },
  {
    "id": 1075,
    "name": "Espace"
  },
  {
    "id": 1076,
    "name": "达斯特"
  },
  {
    "id": 1077,
    "name": "陆风"
  },
  {
    "id": 1078,
    "name": "陆风汽车"
  },
  {
    "id": 1079,
    "name": "陆风X2"
  },
  {
    "id": 1080,
    "name": "逍遥"
  },
  {
    "id": 1081,
    "name": "陆风荣曜"
  },
  {
    "id": 1082,
    "name": "陆风X5"
  },
  {
    "id": 1083,
    "name": "陆风X7"
  },
  {
    "id": 1084,
    "name": "陆风X8"
  },
  {
    "id": 1085,
    "name": "林肯"
  },
  {
    "id": 1086,
    "name": "林肯"
  },
  {
    "id": 1087,
    "name": "MKZ"
  },
  {
    "id": 1088,
    "name": "大陆"
  },
  {
    "id": 1089,
    "name": "MKC"
  },
  {
    "id": 1090,
    "name": "航海家"
  },
  {
    "id": 1091,
    "name": "MKX"
  },
  {
    "id": 1092,
    "name": "领航员"
  },
  {
    "id": 1093,
    "name": "飞行家"
  },
  {
    "id": 1094,
    "name": "飞行家PHEV"
  },
  {
    "id": 1095,
    "name": "领克"
  },
  {
    "id": 1096,
    "name": "领克汽车"
  },
  {
    "id": 1097,
    "name": "领克01"
  },
  {
    "id": 1098,
    "name": "领克01 PHEV"
  },
  {
    "id": 1099,
    "name": "领克02"
  },
  {
    "id": 1100,
    "name": "领克02 PHEV"
  },
  {
    "id": 1101,
    "name": "领克03"
  },
  {
    "id": 1102,
    "name": "领克03 PHEV"
  },
  {
    "id": 1103,
    "name": "力帆"
  },
  {
    "id": 1104,
    "name": "重庆力帆"
  },
  {
    "id": 1105,
    "name": "力帆650"
  },
  {
    "id": 1106,
    "name": "力帆650EV"
  },
  {
    "id": 1107,
    "name": "力帆820"
  },
  {
    "id": 1108,
    "name": "力帆820EV"
  },
  {
    "id": 1109,
    "name": "力帆X50"
  },
  {
    "id": 1110,
    "name": "力帆X60"
  },
  {
    "id": 1111,
    "name": "力帆X80"
  },
  {
    "id": 1112,
    "name": "迈威"
  },
  {
    "id": 1113,
    "name": "迈威EV"
  },
  {
    "id": 1114,
    "name": "乐途"
  },
  {
    "id": 1115,
    "name": "轩朗"
  },
  {
    "id": 1116,
    "name": "理念"
  },
  {
    "id": 1117,
    "name": "理念汽车"
  },
  {
    "id": 1118,
    "name": "理念VE-1"
  },
  {
    "id": 1119,
    "name": "理想汽车"
  },
  {
    "id": 1120,
    "name": "理想汽车"
  },
  {
    "id": 1121,
    "name": "理想ONE"
  },
  {
    "id": 1122,
    "name": "猎豹汽车"
  },
  {
    "id": 1123,
    "name": "猎豹汽车"
  },
  {
    "id": 1124,
    "name": "猎豹CS9"
  },
  {
    "id": 1125,
    "name": "猎豹CS9 EV"
  },
  {
    "id": 1126,
    "name": "猎豹CS10"
  },
  {
    "id": 1127,
    "name": "猎豹Coupe"
  },
  {
    "id": 1128,
    "name": "Mattu"
  },
  {
    "id": 1129,
    "name": "黑金刚"
  },
  {
    "id": 1130,
    "name": "猎豹Q6"
  },
  {
    "id": 1131,
    "name": "猎豹CT7"
  },
  {
    "id": 1132,
    "name": "缤歌"
  },
  {
    "id": 1133,
    "name": "雷克萨斯"
  },
  {
    "id": 1134,
    "name": "雷克萨斯"
  },
  {
    "id": 1135,
    "name": "雷克萨斯CT"
  },
  {
    "id": 1136,
    "name": "雷克萨斯IS"
  },
  {
    "id": 1137,
    "name": "雷克萨斯ES"
  },
  {
    "id": 1138,
    "name": "雷克萨斯GS"
  },
  {
    "id": 1139,
    "name": "雷克萨斯LS"
  },
  {
    "id": 1140,
    "name": "雷克萨斯RC"
  },
  {
    "id": 1141,
    "name": "雷克萨斯LC"
  },
  {
    "id": 1142,
    "name": "雷克萨斯UX"
  },
  {
    "id": 1143,
    "name": "雷克萨斯NX"
  },
  {
    "id": 1144,
    "name": "雷克萨斯RX"
  },
  {
    "id": 1145,
    "name": "雷克萨斯LX"
  },
  {
    "id": 1146,
    "name": "雷克萨斯LM"
  },
  {
    "id": 1147,
    "name": "劳斯莱斯"
  },
  {
    "id": 1148,
    "name": "劳斯莱斯"
  },
  {
    "id": 1149,
    "name": "古思特"
  },
  {
    "id": 1150,
    "name": "幻影"
  },
  {
    "id": 1151,
    "name": "魅影"
  },
  {
    "id": 1152,
    "name": "曜影"
  },
  {
    "id": 1153,
    "name": "库里南"
  },
  {
    "id": 1154,
    "name": "兰博基尼"
  },
  {
    "id": 1155,
    "name": "兰博基尼"
  },
  {
    "id": 1156,
    "name": "Urus"
  },
  {
    "id": 1157,
    "name": "Huracan"
  },
  {
    "id": 1158,
    "name": "Aventador"
  },
  {
    "id": 1159,
    "name": "Centenario"
  },
  {
    "id": 1160,
    "name": "路特斯"
  },
  {
    "id": 1161,
    "name": "路特斯"
  },
  {
    "id": 1162,
    "name": "Elise"
  },
  {
    "id": 1163,
    "name": "Exige"
  },
  {
    "id": 1164,
    "name": "Evora"
  },
  {
    "id": 1165,
    "name": "零跑汽车"
  },
  {
    "id": 1166,
    "name": "零跑汽车"
  },
  {
    "id": 1167,
    "name": "零跑S01"
  },
  {
    "id": 1168,
    "name": "零跑C-more"
  },
  {
    "id": 1169,
    "name": "领途汽车"
  },
  {
    "id": 1170,
    "name": "领途汽车"
  },
  {
    "id": 1171,
    "name": "领途E行"
  },
  {
    "id": 1172,
    "name": "领途K-ONE"
  },
  {
    "id": 1173,
    "name": "陆地方舟"
  },
  {
    "id": 1174,
    "name": "陆地方舟"
  },
  {
    "id": 1175,
    "name": "威途X35"
  },
  {
    "id": 1176,
    "name": "名爵"
  },
  {
    "id": 1177,
    "name": "上汽集团"
  },
  {
    "id": 1178,
    "name": "名爵3"
  },
  {
    "id": 1179,
    "name": "锐行"
  },
  {
    "id": 1180,
    "name": "名爵6"
  },
  {
    "id": 1181,
    "name": "名爵6新能源"
  },
  {
    "id": 1182,
    "name": "名爵6 XPOWER TCR赛车"
  },
  {
    "id": 1183,
    "name": "名爵ZS"
  },
  {
    "id": 1184,
    "name": "名爵EZS"
  },
  {
    "id": 1185,
    "name": "锐腾"
  },
  {
    "id": 1186,
    "name": "名爵HS"
  },
  {
    "id": 1187,
    "name": "MINI"
  },
  {
    "id": 1188,
    "name": "MINI"
  },
  {
    "id": 1189,
    "name": "MINI 3-DOOR"
  },
  {
    "id": 1190,
    "name": "MINI 5-DOOR"
  },
  {
    "id": 1191,
    "name": "MINI CABRIO"
  },
  {
    "id": 1192,
    "name": "MINI CLUBMAN"
  },
  {
    "id": 1193,
    "name": "MINI COUNTRYMAN"
  },
  {
    "id": 1194,
    "name": "MINI JCW"
  },
  {
    "id": 1195,
    "name": "MINI JCW"
  },
  {
    "id": 1196,
    "name": "MINI JCW CLUBMAN"
  },
  {
    "id": 1197,
    "name": "MINI JCW COUNTRYMAN"
  },
  {
    "id": 1198,
    "name": "马自达"
  },
  {
    "id": 1199,
    "name": "一汽马自达"
  },
  {
    "id": 1200,
    "name": "阿特兹"
  },
  {
    "id": 1201,
    "name": "马自达CX-4"
  },
  {
    "id": 1202,
    "name": "长安马自达"
  },
  {
    "id": 1203,
    "name": "昂克赛拉两厢"
  },
  {
    "id": 1204,
    "name": "昂克赛拉三厢"
  },
  {
    "id": 1205,
    "name": "马自达CX-5"
  },
  {
    "id": 1206,
    "name": "马自达CX-8"
  },
  {
    "id": 1207,
    "name": "进口马自达"
  },
  {
    "id": 1208,
    "name": "马自达CX-3"
  },
  {
    "id": 1209,
    "name": "马自达MX-5"
  },
  {
    "id": 1210,
    "name": "迈凯伦"
  },
  {
    "id": 1211,
    "name": "迈凯伦"
  },
  {
    "id": 1212,
    "name": "迈凯伦540C"
  },
  {
    "id": 1213,
    "name": "迈凯伦570S"
  },
  {
    "id": 1214,
    "name": "迈凯伦570GT"
  },
  {
    "id": 1215,
    "name": "迈凯伦600LT"
  },
  {
    "id": 1216,
    "name": "迈凯伦720S"
  },
  {
    "id": 1217,
    "name": "塞纳"
  },
  {
    "id": 1218,
    "name": "玛莎拉蒂"
  },
  {
    "id": 1219,
    "name": "玛莎拉蒂"
  },
  {
    "id": 1220,
    "name": "Ghibli"
  },
  {
    "id": 1221,
    "name": "总裁"
  },
  {
    "id": 1222,
    "name": "Levante"
  },
  {
    "id": 1223,
    "name": "GranTurismo"
  },
  {
    "id": 1224,
    "name": "GranCabrio"
  },
  {
    "id": 1225,
    "name": "摩根"
  },
  {
    "id": 1226,
    "name": "摩根"
  },
  {
    "id": 1227,
    "name": "3-Wheeler"
  },
  {
    "id": 1228,
    "name": "摩根4-4"
  },
  {
    "id": 1229,
    "name": "摩根Plus 4"
  },
  {
    "id": 1230,
    "name": "摩根Plus 8"
  },
  {
    "id": 1231,
    "name": "摩根Aero"
  },
  {
    "id": 1232,
    "name": "摩根Aero 8"
  },
  {
    "id": 1233,
    "name": "摩根Roadster"
  },
  {
    "id": 1234,
    "name": "哪吒汽车"
  },
  {
    "id": 1235,
    "name": "合众新能源"
  },
  {
    "id": 1236,
    "name": "哪吒N01"
  },
  {
    "id": 1237,
    "name": "纳智捷"
  },
  {
    "id": 1238,
    "name": "东风裕隆"
  },
  {
    "id": 1239,
    "name": "锐3"
  },
  {
    "id": 1240,
    "name": "纳5"
  },
  {
    "id": 1241,
    "name": "U5 SUV"
  },
  {
    "id": 1242,
    "name": "U5 EV"
  },
  {
    "id": 1243,
    "name": "优6 SUV"
  },
  {
    "id": 1244,
    "name": "纳智捷URX"
  },
  {
    "id": 1245,
    "name": "大7 MPV"
  },
  {
    "id": 1246,
    "name": "NEVS"
  },
  {
    "id": 1247,
    "name": "国能汽车"
  },
  {
    "id": 1248,
    "name": "NEVS 9-3"
  },
  {
    "id": 1249,
    "name": "NEVS 9-3X"
  },
  {
    "id": 1250,
    "name": "讴歌"
  },
  {
    "id": 1251,
    "name": "广汽讴歌"
  },
  {
    "id": 1252,
    "name": "讴歌TLX-L"
  },
  {
    "id": 1253,
    "name": "讴歌CDX"
  },
  {
    "id": 1254,
    "name": "讴歌RDX"
  },
  {
    "id": 1255,
    "name": "进口讴歌"
  },
  {
    "id": 1256,
    "name": "讴歌MDX"
  },
  {
    "id": 1257,
    "name": "讴歌NSX"
  },
  {
    "id": 1258,
    "name": "欧拉"
  },
  {
    "id": 1259,
    "name": "欧拉"
  },
  {
    "id": 1260,
    "name": "欧拉R1"
  },
  {
    "id": 1261,
    "name": "欧拉R2"
  },
  {
    "id": 1262,
    "name": "欧拉iQ"
  },
  {
    "id": 1263,
    "name": "欧联汽车"
  },
  {
    "id": 1264,
    "name": "广马汽车"
  },
  {
    "id": 1265,
    "name": "欧联M1"
  },
  {
    "id": 1266,
    "name": "Polestar极星"
  },
  {
    "id": 1267,
    "name": "Polestar"
  },
  {
    "id": 1268,
    "name": "Polestar 1"
  },
  {
    "id": 1269,
    "name": "Polestar 2"
  },
  {
    "id": 1270,
    "name": "起亚"
  },
  {
    "id": 1271,
    "name": "东风悦达起亚"
  },
  {
    "id": 1272,
    "name": "KX CROSS"
  },
  {
    "id": 1273,
    "name": "焕驰"
  },
  {
    "id": 1274,
    "name": "起亚K2"
  },
  {
    "id": 1275,
    "name": "福瑞迪"
  },
  {
    "id": 1276,
    "name": "起亚K3"
  },
  {
    "id": 1277,
    "name": "起亚K3 PHEV"
  },
  {
    "id": 1278,
    "name": "凯绅"
  },
  {
    "id": 1279,
    "name": "起亚K4"
  },
  {
    "id": 1280,
    "name": "起亚K5"
  },
  {
    "id": 1281,
    "name": "起亚K5 PHEV"
  },
  {
    "id": 1282,
    "name": "奕跑"
  },
  {
    "id": 1283,
    "name": "智跑"
  },
  {
    "id": 1284,
    "name": "起亚KX3"
  },
  {
    "id": 1285,
    "name": "起亚KX3 EV"
  },
  {
    "id": 1286,
    "name": "起亚KX5"
  },
  {
    "id": 1287,
    "name": "起亚KX7"
  },
  {
    "id": 1288,
    "name": "进口起亚"
  },
  {
    "id": 1289,
    "name": "起亚K9"
  },
  {
    "id": 1290,
    "name": "斯汀格"
  },
  {
    "id": 1291,
    "name": "极睿"
  },
  {
    "id": 1292,
    "name": "索兰托L"
  },
  {
    "id": 1293,
    "name": "霸锐"
  },
  {
    "id": 1294,
    "name": "佳乐"
  },
  {
    "id": 1295,
    "name": "嘉华"
  },
  {
    "id": 1296,
    "name": "奇瑞"
  },
  {
    "id": 1297,
    "name": "奇瑞"
  },
  {
    "id": 1298,
    "name": "奇瑞eQ1"
  },
  {
    "id": 1299,
    "name": "艾瑞泽5"
  },
  {
    "id": 1300,
    "name": "艾瑞泽5e"
  },
  {
    "id": 1301,
    "name": "艾瑞泽GX"
  },
  {
    "id": 1302,
    "name": "艾瑞泽7"
  },
  {
    "id": 1303,
    "name": "瑞虎e"
  },
  {
    "id": 1304,
    "name": "瑞虎3X"
  },
  {
    "id": 1305,
    "name": "瑞虎3xe"
  },
  {
    "id": 1306,
    "name": "瑞虎3"
  },
  {
    "id": 1307,
    "name": "瑞虎5x"
  },
  {
    "id": 1308,
    "name": "瑞虎5"
  },
  {
    "id": 1309,
    "name": "瑞虎7"
  },
  {
    "id": 1310,
    "name": "瑞虎8"
  },
  {
    "id": 1311,
    "name": "前途"
  },
  {
    "id": 1312,
    "name": "前途汽车"
  },
  {
    "id": 1313,
    "name": "前途K50"
  },
  {
    "id": 1314,
    "name": "前途K20"
  },
  {
    "id": 1315,
    "name": "前途K25"
  },
  {
    "id": 1316,
    "name": "全球鹰"
  },
  {
    "id": 1317,
    "name": "康迪全球鹰"
  },
  {
    "id": 1318,
    "name": "全球鹰EX3"
  },
  {
    "id": 1319,
    "name": "全球鹰K12"
  },
  {
    "id": 1320,
    "name": "全球鹰K17"
  },
  {
    "id": 1321,
    "name": "全球鹰K27"
  },
  {
    "id": 1322,
    "name": "清源汽车"
  },
  {
    "id": 1323,
    "name": "清源汽车"
  },
  {
    "id": 1324,
    "name": "清源小尊"
  },
  {
    "id": 1325,
    "name": "清源尊者"
  },
  {
    "id": 1326,
    "name": "庆铃汽车"
  },
  {
    "id": 1327,
    "name": "庆铃汽车"
  },
  {
    "id": 1328,
    "name": "庆铃TAGA"
  },
  {
    "id": 1329,
    "name": "乔治·巴顿"
  },
  {
    "id": 1330,
    "name": "乔治·巴顿"
  },
  {
    "id": 1331,
    "name": "战剑"
  },
  {
    "id": 1332,
    "name": "战车"
  },
  {
    "id": 1333,
    "name": "日产"
  },
  {
    "id": 1334,
    "name": "东风日产"
  },
  {
    "id": 1335,
    "name": "玛驰"
  },
  {
    "id": 1336,
    "name": "骊威"
  },
  {
    "id": 1337,
    "name": "阳光"
  },
  {
    "id": 1338,
    "name": "骐达"
  },
  {
    "id": 1339,
    "name": "新蓝鸟"
  },
  {
    "id": 1340,
    "name": "轩逸"
  },
  {
    "id": 1341,
    "name": "轩逸经典"
  },
  {
    "id": 1342,
    "name": "轩逸·纯电"
  },
  {
    "id": 1343,
    "name": "天籁"
  },
  {
    "id": 1344,
    "name": "西玛"
  },
  {
    "id": 1345,
    "name": "劲客"
  },
  {
    "id": 1346,
    "name": "逍客"
  },
  {
    "id": 1347,
    "name": "途达"
  },
  {
    "id": 1348,
    "name": "奇骏"
  },
  {
    "id": 1349,
    "name": "楼兰"
  },
  {
    "id": 1350,
    "name": "郑州日产"
  },
  {
    "id": 1351,
    "name": "途达"
  },
  {
    "id": 1352,
    "name": "日产NV200"
  },
  {
    "id": 1353,
    "name": "纳瓦拉"
  },
  {
    "id": 1354,
    "name": "进口日产"
  },
  {
    "id": 1355,
    "name": "途乐"
  },
  {
    "id": 1356,
    "name": "贵士"
  },
  {
    "id": 1357,
    "name": "日产370Z"
  },
  {
    "id": 1358,
    "name": "日产GT-R"
  },
  {
    "id": 1359,
    "name": "碧莲"
  },
  {
    "id": 1360,
    "name": "荣威"
  },
  {
    "id": 1361,
    "name": "上汽集团"
  },
  {
    "id": 1362,
    "name": "荣威360"
  },
  {
    "id": 1363,
    "name": "荣威i5"
  },
  {
    "id": 1364,
    "name": "荣威Ei5"
  },
  {
    "id": 1365,
    "name": "荣威i6"
  },
  {
    "id": 1366,
    "name": "荣威ei6"
  },
  {
    "id": 1367,
    "name": "荣威950"
  },
  {
    "id": 1368,
    "name": "荣威e950"
  },
  {
    "id": 1369,
    "name": "荣威RX3"
  },
  {
    "id": 1370,
    "name": "荣威RX5"
  },
  {
    "id": 1371,
    "name": "荣威eRX5"
  },
  {
    "id": 1372,
    "name": "荣威ERX5"
  },
  {
    "id": 1373,
    "name": "荣威RX8"
  },
  {
    "id": 1374,
    "name": "荣威MAX"
  },
  {
    "id": 1375,
    "name": "荣威MARVEL X"
  },
  {
    "id": 1376,
    "name": "瑞迈"
  },
  {
    "id": 1377,
    "name": "江西五十铃"
  },
  {
    "id": 1378,
    "name": "瑞迈"
  },
  {
    "id": 1379,
    "name": "如虎"
  },
  {
    "id": 1380,
    "name": "如虎"
  },
  {
    "id": 1381,
    "name": "如虎RXL"
  },
  {
    "id": 1382,
    "name": "如虎Rt 12 R"
  },
  {
    "id": 1383,
    "name": "如虎CTR 3"
  },
  {
    "id": 1384,
    "name": "smart"
  },
  {
    "id": 1385,
    "name": "smart"
  },
  {
    "id": 1386,
    "name": "smart fortwo"
  },
  {
    "id": 1387,
    "name": "smart forfour"
  },
  {
    "id": 1388,
    "name": "SERES"
  },
  {
    "id": 1389,
    "name": "金康SERES"
  },
  {
    "id": 1390,
    "name": "SF5"
  },
  {
    "id": 1391,
    "name": "SF7"
  },
  {
    "id": 1392,
    "name": "三菱"
  },
  {
    "id": 1393,
    "name": "进口三菱"
  },
  {
    "id": 1394,
    "name": "帕杰罗"
  },
  {
    "id": 1395,
    "name": "广汽三菱"
  },
  {
    "id": 1396,
    "name": "劲炫"
  },
  {
    "id": 1397,
    "name": "奕歌"
  },
  {
    "id": 1398,
    "name": "欧蓝德"
  },
  {
    "id": 1399,
    "name": "祺智EV"
  },
  {
    "id": 1400,
    "name": "祺智PHEV"
  },
  {
    "id": 1401,
    "name": "思铭"
  },
  {
    "id": 1402,
    "name": "东风本田"
  },
  {
    "id": 1403,
    "name": "思铭X-NV"
  },
  {
    "id": 1404,
    "name": "斯柯达"
  },
  {
    "id": 1405,
    "name": "上汽斯柯达"
  },
  {
    "id": 1406,
    "name": "晶锐"
  },
  {
    "id": 1407,
    "name": "昕动"
  },
  {
    "id": 1408,
    "name": "昕锐"
  },
  {
    "id": 1409,
    "name": "明锐"
  },
  {
    "id": 1410,
    "name": "明锐旅行车"
  },
  {
    "id": 1411,
    "name": "速派"
  },
  {
    "id": 1412,
    "name": "柯米克"
  },
  {
    "id": 1413,
    "name": "柯珞克"
  },
  {
    "id": 1414,
    "name": "柯迪亚克"
  },
  {
    "id": 1415,
    "name": "柯迪亚克GT"
  },
  {
    "id": 1416,
    "name": "斯巴鲁"
  },
  {
    "id": 1417,
    "name": "进口斯巴鲁"
  },
  {
    "id": 1418,
    "name": "力狮"
  },
  {
    "id": 1419,
    "name": "斯巴鲁XV"
  },
  {
    "id": 1420,
    "name": "森林人"
  },
  {
    "id": 1421,
    "name": "傲虎"
  },
  {
    "id": 1422,
    "name": "斯巴鲁BRZ"
  },
  {
    "id": 1423,
    "name": "斯威汽车"
  },
  {
    "id": 1424,
    "name": "华晨鑫源"
  },
  {
    "id": 1425,
    "name": "斯威G01"
  },
  {
    "id": 1426,
    "name": "斯威G05"
  },
  {
    "id": 1427,
    "name": "斯威X2"
  },
  {
    "id": 1428,
    "name": "斯威X3"
  },
  {
    "id": 1429,
    "name": "斯威X7"
  },
  {
    "id": 1430,
    "name": "斯威G01 EV"
  },
  {
    "id": 1431,
    "name": "思皓SOL"
  },
  {
    "id": 1432,
    "name": "江淮大众"
  },
  {
    "id": 1433,
    "name": "SOL E20X"
  },
  {
    "id": 1434,
    "name": "上汽大通"
  },
  {
    "id": 1435,
    "name": "上汽大通"
  },
  {
    "id": 1436,
    "name": "大通D60"
  },
  {
    "id": 1437,
    "name": "大通D60e"
  },
  {
    "id": 1438,
    "name": "大通D90"
  },
  {
    "id": 1439,
    "name": "大通G50"
  },
  {
    "id": 1440,
    "name": "大通EG50"
  },
  {
    "id": 1441,
    "name": "大通G10"
  },
  {
    "id": 1442,
    "name": "大通EG10"
  },
  {
    "id": 1443,
    "name": "大通G20"
  },
  {
    "id": 1444,
    "name": "大通V80"
  },
  {
    "id": 1445,
    "name": "大通FCV80"
  },
  {
    "id": 1446,
    "name": "大通V90"
  },
  {
    "id": 1447,
    "name": "大通T60"
  },
  {
    "id": 1448,
    "name": "大通T70"
  },
  {
    "id": 1449,
    "name": "大通EV30"
  },
  {
    "id": 1450,
    "name": "双龙"
  },
  {
    "id": 1451,
    "name": "双龙"
  },
  {
    "id": 1452,
    "name": "主席"
  },
  {
    "id": 1453,
    "name": "蒂维拉"
  },
  {
    "id": 1454,
    "name": "柯兰多"
  },
  {
    "id": 1455,
    "name": "途凌"
  },
  {
    "id": 1456,
    "name": "爱腾"
  },
  {
    "id": 1457,
    "name": "雷斯特"
  },
  {
    "id": 1458,
    "name": "雷斯特W"
  },
  {
    "id": 1459,
    "name": "路帝"
  },
  {
    "id": 1460,
    "name": "斯达泰克"
  },
  {
    "id": 1461,
    "name": "斯达泰克"
  },
  {
    "id": 1462,
    "name": "斯达泰克卫士"
  },
  {
    "id": 1463,
    "name": "赛麟"
  },
  {
    "id": 1464,
    "name": "赛麟"
  },
  {
    "id": 1465,
    "name": "赛麟S1"
  },
  {
    "id": 1466,
    "name": "赛麟"
  },
  {
    "id": 1467,
    "name": "迈迈"
  },
  {
    "id": 1468,
    "name": "陕西通家"
  },
  {
    "id": 1469,
    "name": " 陕西通家"
  },
  {
    "id": 1470,
    "name": "电牛二号"
  },
  {
    "id": 1471,
    "name": "腾势"
  },
  {
    "id": 1472,
    "name": "腾势"
  },
  {
    "id": 1473,
    "name": "腾势"
  },
  {
    "id": 1474,
    "name": "特斯拉"
  },
  {
    "id": 1475,
    "name": "特斯拉中国"
  },
  {
    "id": 1476,
    "name": "Model 3"
  },
  {
    "id": 1477,
    "name": "进口特斯拉"
  },
  {
    "id": 1478,
    "name": "Model 3"
  },
  {
    "id": 1479,
    "name": "Model S"
  },
  {
    "id": 1480,
    "name": "Model X"
  },
  {
    "id": 1481,
    "name": "Model Y"
  },
  {
    "id": 1482,
    "name": "泰克鲁斯·腾风"
  },
  {
    "id": 1483,
    "name": "泰克鲁斯·腾风"
  },
  {
    "id": 1484,
    "name": "GT96 TREV"
  },
  {
    "id": 1485,
    "name": "天际汽车"
  },
  {
    "id": 1486,
    "name": "天际汽车"
  },
  {
    "id": 1487,
    "name": "天际ME7"
  },
  {
    "id": 1488,
    "name": "天际ME-S"
  },
  {
    "id": 1489,
    "name": "WEY"
  },
  {
    "id": 1490,
    "name": "长城汽车"
  },
  {
    "id": 1491,
    "name": "WEY VV5"
  },
  {
    "id": 1492,
    "name": "WEY VV6"
  },
  {
    "id": 1493,
    "name": "WEY VV7"
  },
  {
    "id": 1494,
    "name": "WEY P8"
  },
  {
    "id": 1495,
    "name": "五菱"
  },
  {
    "id": 1496,
    "name": "上汽通用五菱"
  },
  {
    "id": 1497,
    "name": "宏光S3"
  },
  {
    "id": 1498,
    "name": "宏光V"
  },
  {
    "id": 1499,
    "name": "荣光"
  },
  {
    "id": 1500,
    "name": "荣光V"
  },
  {
    "id": 1501,
    "name": "五菱之光"
  },
  {
    "id": 1502,
    "name": "五菱之光V"
  },
  {
    "id": 1503,
    "name": "沃尔沃"
  },
  {
    "id": 1504,
    "name": "沃尔沃亚太"
  },
  {
    "id": 1505,
    "name": "沃尔沃S60L"
  },
  {
    "id": 1506,
    "name": "沃尔沃S60L E驱混动"
  },
  {
    "id": 1507,
    "name": "沃尔沃S90"
  },
  {
    "id": 1508,
    "name": "沃尔沃S90 E驱混动"
  },
  {
    "id": 1509,
    "name": "沃尔沃XC40"
  },
  {
    "id": 1510,
    "name": "沃尔沃XC60"
  },
  {
    "id": 1511,
    "name": "沃尔沃XC60 E驱混动"
  },
  {
    "id": 1512,
    "name": "进口沃尔沃"
  },
  {
    "id": 1513,
    "name": "沃尔沃V40"
  },
  {
    "id": 1514,
    "name": "沃尔沃S60"
  },
  {
    "id": 1515,
    "name": "沃尔沃S60 Polestar"
  },
  {
    "id": 1516,
    "name": "沃尔沃V60"
  },
  {
    "id": 1517,
    "name": "沃尔沃V60 Polestar"
  },
  {
    "id": 1518,
    "name": "沃尔沃V90"
  },
  {
    "id": 1519,
    "name": "沃尔沃XC40"
  },
  {
    "id": 1520,
    "name": "沃尔沃XC90"
  },
  {
    "id": 1521,
    "name": "沃尔沃XC90 E驱混动"
  },
  {
    "id": 1522,
    "name": "五十铃"
  },
  {
    "id": 1523,
    "name": "江西五十铃"
  },
  {
    "id": 1524,
    "name": "铃拓"
  },
  {
    "id": 1525,
    "name": "D-MAX"
  },
  {
    "id": 1526,
    "name": "mu-X牧游侠"
  },
  {
    "id": 1527,
    "name": "潍柴英致"
  },
  {
    "id": 1528,
    "name": "潍柴汽车"
  },
  {
    "id": 1529,
    "name": "英致EX1"
  },
  {
    "id": 1530,
    "name": "英致G3"
  },
  {
    "id": 1531,
    "name": "英致G5"
  },
  {
    "id": 1532,
    "name": "英致727"
  },
  {
    "id": 1533,
    "name": "英致737"
  },
  {
    "id": 1534,
    "name": "英致737EV"
  },
  {
    "id": 1535,
    "name": "蔚来汽车"
  },
  {
    "id": 1536,
    "name": "蔚来汽车"
  },
  {
    "id": 1537,
    "name": "蔚来ET"
  },
  {
    "id": 1538,
    "name": "蔚来ES6"
  },
  {
    "id": 1539,
    "name": "蔚来ES8"
  },
  {
    "id": 1540,
    "name": "蔚来EP9"
  },
  {
    "id": 1541,
    "name": "威马汽车"
  },
  {
    "id": 1542,
    "name": "威马汽车"
  },
  {
    "id": 1543,
    "name": "威马EX5"
  },
  {
    "id": 1544,
    "name": "威马EX6"
  },
  {
    "id": 1545,
    "name": "现代"
  },
  {
    "id": 1546,
    "name": "北京现代"
  },
  {
    "id": 1547,
    "name": "瑞纳"
  },
  {
    "id": 1548,
    "name": "悦纳"
  },
  {
    "id": 1549,
    "name": "悦纳RV"
  },
  {
    "id": 1550,
    "name": "伊兰特EV"
  },
  {
    "id": 1551,
    "name": "悦动"
  },
  {
    "id": 1552,
    "name": "逸行"
  },
  {
    "id": 1553,
    "name": "领动"
  },
  {
    "id": 1554,
    "name": "领动PHEV"
  },
  {
    "id": 1555,
    "name": "菲斯塔"
  },
  {
    "id": 1556,
    "name": "名图"
  },
  {
    "id": 1557,
    "name": "索纳塔"
  },
  {
    "id": 1558,
    "name": "索纳塔PHEV"
  },
  {
    "id": 1559,
    "name": "ENCINO 昂希诺"
  },
  {
    "id": 1560,
    "name": "昂希诺纯电动"
  },
  {
    "id": 1561,
    "name": "现代ix25"
  },
  {
    "id": 1562,
    "name": "现代ix35"
  },
  {
    "id": 1563,
    "name": "途胜"
  },
  {
    "id": 1564,
    "name": "胜达"
  },
  {
    "id": 1565,
    "name": "进口现代"
  },
  {
    "id": 1566,
    "name": "Veloster飞思"
  },
  {
    "id": 1567,
    "name": "雅尊"
  },
  {
    "id": 1568,
    "name": "捷恩斯"
  },
  {
    "id": 1569,
    "name": "格越"
  },
  {
    "id": 1570,
    "name": "H-1辉翼"
  },
  {
    "id": 1571,
    "name": "四川现代"
  },
  {
    "id": 1572,
    "name": "康恩迪"
  },
  {
    "id": 1573,
    "name": "雪佛兰"
  },
  {
    "id": 1574,
    "name": "上汽通用雪佛兰"
  },
  {
    "id": 1575,
    "name": "赛欧3"
  },
  {
    "id": 1576,
    "name": "乐风RV"
  },
  {
    "id": 1577,
    "name": "科沃兹"
  },
  {
    "id": 1578,
    "name": "新科鲁兹"
  },
  {
    "id": 1579,
    "name": "新科鲁兹两厢"
  },
  {
    "id": 1580,
    "name": "科鲁泽"
  },
  {
    "id": 1581,
    "name": "沃兰多"
  },
  {
    "id": 1582,
    "name": "迈锐宝XL"
  },
  {
    "id": 1583,
    "name": "创酷"
  },
  {
    "id": 1584,
    "name": "创界"
  },
  {
    "id": 1585,
    "name": "探界者"
  },
  {
    "id": 1586,
    "name": "进口雪佛兰"
  },
  {
    "id": 1587,
    "name": "科迈罗"
  },
  {
    "id": 1588,
    "name": "科尔维特"
  },
  {
    "id": 1589,
    "name": "库罗德"
  },
  {
    "id": 1590,
    "name": "索罗德"
  },
  {
    "id": 1591,
    "name": "雪铁龙"
  },
  {
    "id": 1592,
    "name": "东风雪铁龙"
  },
  {
    "id": 1593,
    "name": "爱丽舍"
  },
  {
    "id": 1594,
    "name": "C4世嘉"
  },
  {
    "id": 1595,
    "name": "雪铁龙C4L"
  },
  {
    "id": 1596,
    "name": "雪铁龙C5"
  },
  {
    "id": 1597,
    "name": "雪铁龙C6"
  },
  {
    "id": 1598,
    "name": "雪铁龙C3-XR"
  },
  {
    "id": 1599,
    "name": "云逸 C4 AIRCROSS"
  },
  {
    "id": 1600,
    "name": "天逸 C5 AIRCROSS"
  },
  {
    "id": 1601,
    "name": "进口雪铁龙"
  },
  {
    "id": 1602,
    "name": "C4 PICASSO"
  },
  {
    "id": 1603,
    "name": "新特"
  },
  {
    "id": 1604,
    "name": "新特"
  },
  {
    "id": 1605,
    "name": "新特DEV1"
  },
  {
    "id": 1606,
    "name": "鑫源新能源"
  },
  {
    "id": 1607,
    "name": "华晨鑫源"
  },
  {
    "id": 1608,
    "name": "新海狮EV"
  },
  {
    "id": 1609,
    "name": "小鹏汽车"
  },
  {
    "id": 1610,
    "name": "小鹏汽车"
  },
  {
    "id": 1611,
    "name": "小鹏汽车G3"
  },
  {
    "id": 1612,
    "name": "小鹏汽车P7"
  },
  {
    "id": 1613,
    "name": "星途"
  },
  {
    "id": 1614,
    "name": "星途"
  },
  {
    "id": 1615,
    "name": "星途-LX"
  },
  {
    "id": 1616,
    "name": "星途-TX"
  },
  {
    "id": 1617,
    "name": "英菲尼迪"
  },
  {
    "id": 1618,
    "name": "东风英菲尼迪"
  },
  {
    "id": 1619,
    "name": "英菲尼迪Q50L"
  },
  {
    "id": 1620,
    "name": "英菲尼迪QX50"
  },
  {
    "id": 1621,
    "name": "进口英菲尼迪"
  },
  {
    "id": 1622,
    "name": "英菲尼迪Q50"
  },
  {
    "id": 1623,
    "name": "英菲尼迪Q60"
  },
  {
    "id": 1624,
    "name": "英菲尼迪Q70L"
  },
  {
    "id": 1625,
    "name": "英菲尼迪ESQ"
  },
  {
    "id": 1626,
    "name": "英菲尼迪QX30"
  },
  {
    "id": 1627,
    "name": "英菲尼迪QX60"
  },
  {
    "id": 1628,
    "name": "英菲尼迪QX70"
  },
  {
    "id": 1629,
    "name": "英菲尼迪QX80"
  },
  {
    "id": 1630,
    "name": "驭胜"
  },
  {
    "id": 1631,
    "name": "江铃汽车"
  },
  {
    "id": 1632,
    "name": "驭胜S330"
  },
  {
    "id": 1633,
    "name": "驭胜S350"
  },
  {
    "id": 1634,
    "name": "一汽"
  },
  {
    "id": 1635,
    "name": "天津一汽"
  },
  {
    "id": 1636,
    "name": "威志V5"
  },
  {
    "id": 1637,
    "name": "夏利N5"
  },
  {
    "id": 1638,
    "name": "夏利N7"
  },
  {
    "id": 1639,
    "name": "骏派A50"
  },
  {
    "id": 1640,
    "name": "骏派A70"
  },
  {
    "id": 1641,
    "name": "骏派A70E"
  },
  {
    "id": 1642,
    "name": "骏派CX65"
  },
  {
    "id": 1643,
    "name": "骏派D60"
  },
  {
    "id": 1644,
    "name": "骏派D80"
  },
  {
    "id": 1645,
    "name": "一汽吉林"
  },
  {
    "id": 1646,
    "name": "森雅R7"
  },
  {
    "id": 1647,
    "name": "森雅R7 EV"
  },
  {
    "id": 1648,
    "name": "森雅R8"
  },
  {
    "id": 1649,
    "name": "森雅R9"
  },
  {
    "id": 1650,
    "name": "佳宝V75"
  },
  {
    "id": 1651,
    "name": "佳宝V77"
  },
  {
    "id": 1652,
    "name": "佳宝V80"
  },
  {
    "id": 1653,
    "name": "一汽红塔"
  },
  {
    "id": 1654,
    "name": "蓝舰T340"
  },
  {
    "id": 1655,
    "name": "野马汽车"
  },
  {
    "id": 1656,
    "name": "野马汽车"
  },
  {
    "id": 1657,
    "name": "博骏"
  },
  {
    "id": 1658,
    "name": "野马EC60"
  },
  {
    "id": 1659,
    "name": "野马T70"
  },
  {
    "id": 1660,
    "name": "野马T80"
  },
  {
    "id": 1661,
    "name": "斯派卡"
  },
  {
    "id": 1662,
    "name": "野马EC70"
  },
  {
    "id": 1663,
    "name": "野马EC30"
  },
  {
    "id": 1664,
    "name": "依维柯"
  },
  {
    "id": 1665,
    "name": "南京依维柯"
  },
  {
    "id": 1666,
    "name": "Daily欧胜"
  },
  {
    "id": 1667,
    "name": "裕路汽车"
  },
  {
    "id": 1668,
    "name": "裕路汽车"
  },
  {
    "id": 1669,
    "name": "裕路EV2"
  },
  {
    "id": 1670,
    "name": "云度"
  },
  {
    "id": 1671,
    "name": "云度"
  },
  {
    "id": 1672,
    "name": "云度π1"
  },
  {
    "id": 1673,
    "name": "云度π3"
  },
  {
    "id": 1674,
    "name": "云度π7"
  },
  {
    "id": 1675,
    "name": "云雀汽车"
  },
  {
    "id": 1676,
    "name": "云雀汽车"
  },
  {
    "id": 1677,
    "name": "云雀Q1"
  },
  {
    "id": 1678,
    "name": "中华"
  },
  {
    "id": 1679,
    "name": "华晨中华"
  },
  {
    "id": 1680,
    "name": "中华H230EV"
  },
  {
    "id": 1681,
    "name": "中华H3"
  },
  {
    "id": 1682,
    "name": "中华H530"
  },
  {
    "id": 1683,
    "name": "中华V3"
  },
  {
    "id": 1684,
    "name": "中华V6"
  },
  {
    "id": 1685,
    "name": "中华V7"
  },
  {
    "id": 1686,
    "name": "众泰"
  },
  {
    "id": 1687,
    "name": "众泰汽车"
  },
  {
    "id": 1688,
    "name": "芝麻"
  },
  {
    "id": 1689,
    "name": "云100"
  },
  {
    "id": 1690,
    "name": "众泰E200"
  },
  {
    "id": 1691,
    "name": "众泰Z360"
  },
  {
    "id": 1692,
    "name": "众泰Z500EV"
  },
  {
    "id": 1693,
    "name": "众泰Z560"
  },
  {
    "id": 1694,
    "name": "众泰Z700H"
  },
  {
    "id": 1695,
    "name": "众泰T300"
  },
  {
    "id": 1696,
    "name": "众泰T300EV"
  },
  {
    "id": 1697,
    "name": "众泰T500"
  },
  {
    "id": 1698,
    "name": "众泰T600"
  },
  {
    "id": 1699,
    "name": "众泰T600 Coupe"
  },
  {
    "id": 1700,
    "name": "众泰T700"
  },
  {
    "id": 1701,
    "name": "众泰T800"
  },
  {
    "id": 1702,
    "name": "众泰SR7"
  },
  {
    "id": 1703,
    "name": "众泰SR9"
  },
  {
    "id": 1704,
    "name": "大迈X5"
  },
  {
    "id": 1705,
    "name": "大迈X7"
  },
  {
    "id": 1706,
    "name": "众泰A16"
  },
  {
    "id": 1707,
    "name": "中兴"
  },
  {
    "id": 1708,
    "name": "广汽中兴"
  },
  {
    "id": 1709,
    "name": "中兴C3"
  },
  {
    "id": 1710,
    "name": "中兴GX3"
  },
  {
    "id": 1711,
    "name": "中兴汽车"
  },
  {
    "id": 1712,
    "name": "小老虎"
  },
  {
    "id": 1713,
    "name": "威虎"
  },
  {
    "id": 1714,
    "name": "领主"
  },
  {
    "id": 1715,
    "name": "之诺"
  },
  {
    "id": 1716,
    "name": "华晨宝马"
  },
  {
    "id": 1717,
    "name": "之诺60H"
  },
  {
    "id": 1718,
    "name": "之诺1E"
  },
  {
    "id": 1719,
    "name": "知豆"
  },
  {
    "id": 1720,
    "name": "知豆电动车"
  },
  {
    "id": 1721,
    "name": "知豆D2"
  },
  {
    "id": 1722,
    "name": "知豆D2S"
  },
  {
    "id": 1723,
    "name": "知豆D3"
  },
  {
    "id": 1724,
    "name": "正道"
  },
  {
    "id": 1725,
    "name": "正道"
  },
  {
    "id": 1726,
    "name": "正道GT"
  },
  {
    "id": 1727,
    "name": "正道H500"
  },
  {
    "id": 1728,
    "name": "正道H600"
  },
  {
    "id": 1729,
    "name": "正道K350"
  },
  {
    "id": 1730,
    "name": "正道K550"
  },
  {
    "id": 1731,
    "name": "正道K750"
  }
]